Workbook
Name BusinessCapabilities: #REF!
Name Domain: #REF!

Sheet Sri - Resource Master -May 
A1: Yash Emp ID | B1: Employee Name | C1: Grade | D1: Client | E1: Project | F1: Skill | G1: Delivery Manager | H1: IRM Name | I1: SRM Name | J1: Client Manager | M1: Allocation Type | N1: Billing Rate | O1: %Profit
A2: 1000111 | B2: Madhu Smitha | C2: E5 | D2: JohnDeere | E2: TCI Staffing | F2: SAP FICO | G2: Srivijaya Pichika | H2: Srivijaya Pichika | I2: Srivijaya Pichika | J2: Dipesh Parekh | K2: =VLOOKUP(A2,'Employee detail'!$B$1:$F$220,5,0) -> IT Finance | L2: IT Finance | M2: Billable | N2: 2100 | O2: 0.42911905
A3: 1009797 | B3: Vivek Anaskar | C3: E2 | D3: JohnDeere | E3: TCI Staffing | F3: SAP HCM | G3: Srivijaya Pichika | H3: Nishanta Devadiga | I3: Srivijaya Pichika | J3: Suresh Manthathi | K3: =VLOOKUP(A3,'Employee detail'!$B$1:$F$220,5,0) -> HCM | L3: HR | M3: Billable | N3: 2100 | O3: 0.30933333
A4: 1601237 | B4: Akshay Upalekar | C4: C | D4: JohnDeere | E4: TCI Staffing | F4: SAP EWM | G4: Srivijaya Pichika | H4: Nishanta Devadiga | I4: Srivijaya Pichika | J4: Venkata Anil Krishna Poluri | K4: =VLOOKUP(A4,'Employee detail'!$B$1:$F$220,5,0) -> PDC | M4: Billable | N4: 1800 | O4: 0.33333333
A5: 1005949 | B5: B Sreedhar Reddy | C5: E6 | D5: JohnDeere | E5: TCI Staffing | F5: SAP CRM | G5: Srivijaya Pichika | H5: Srivijaya Pichika | I5: Srivijaya Pichika | J5: Sreedhar Nimmagadda | K5: =VLOOKUP(A5,'Employee detail'!$B$1:$F$220,5,0) -> PDC | L5: PDC | M5: Billable | N5: 1500 | O5: -0.022566667
A6: 1012709 | B6: Kovvuru Chandra Reddy | C6: E1 | D6: JohnDeere | E6: TCI Staffing | F6: SAP BODS | G6: Srivijaya Pichika | H6: Srivijaya Pichika | I6: Srivijaya Pichika | J6: Pranjali Patil | K6: =VLOOKUP(A6,'Employee detail'!$B$1:$F$220,5,0) -> PDC | L6: PDC | M6: Billable | N6: 1400 | O6: 0.63885714
A7: 1005201 | B7: Vijaya Ganapa | C7: E2 | D7: JohnDeere | E7: TCI Staffing | F7: SAP SuccessFactors | G7: Srivijaya Pichika | H7: Nishanta Devadiga | I7: Sharath Panaggamula | J7: Suresh Manthathi | K7: =VLOOKUP(A7,'Employee detail'!$B$1:$F$220,5,0) -> HCM | L7: HR | M7: Billable | N7: 1800 | O7: 0.54711111
A8: 1012589 | B8: Sowjanya Parthasarathi | C8: E2 | D8: JohnDeere | E8: System Interoperability | F8: SAP PI/CPI | G8: Srivijaya Pichika | H8: Abir Sarkar | I8: Srivijaya Pichika | J8: Mahesh Jayaraman | K8: =VLOOKUP(A8,'Employee detail'!$B$1:$F$220,5,0) -> MSP | L8: MSP | M8: Billable | N8: 1640 | O8: 0.18699187
A9: 1012968 | B9: Narasimha Reddy Kanubuddi | C9: E2 | D9: JohnDeere | E9: TCI Staffing | F9: SAP ABAP HANA | G9: Srivijaya Pichika | H9: Nishanta Devadiga | I9: Srivijaya Pichika | J9: Atul Kudegave | K9: MSP | M9: Billable | N9: 1800 | O9: 0.54552778
A10: 1014344 | B10: Sathi Manikanta Ramareddy | C10: E1 | D10: JohnDeere | E10: TCI Staffing | F10: SAP BODS | G10: Srivijaya Pichika | H10: Srivijaya Pichika | I10: Srivijaya Pichika | J10: Pranjali Patil | K10: =VLOOKUP(A10,'Employee detail'!$B$1:$F$220,5,0) -> PDC | M10: Billable | N10: 1700 | O10: 0.72985294
A11: 1601466 | B11: Sreedevi Varahala | C11: C | D11: JohnDeere | E11: TCI Staffing | F11: SAP ABAP CRM | G11: Srivijaya Pichika | H11: Srivijaya Pichika | I11: Srivijaya Pichika | J11: Sreedhar Nimmagadda | K11: =VLOOKUP(A11,'Employee detail'!$B$1:$F$220,5,0) -> PDC | M11: Billable | N11: 2200 | O11: 0.43181818
A12: 1600057 | B12: Afsar Mohammad | C12: E2 | D12: JohnDeere | E12: TCI Staffing | F12: SAP BODS | G12: Srivijaya Pichika | H12: Srivijaya Pichika | I12: Srivijaya Pichika | J12: Pranjali Patil | K12: =VLOOKUP(A12,'Employee detail'!$B$1:$F$220,5,0) -> PDC | M12: Billable | N12: 1800 | O12: 0.45508333
A13: 1601535 | B13: Yanamadala Sasidhar | C13: C | D13: JohnDeere | E13: TCI Staffing | F13: SAP ABAP CRM | G13: Srivijaya Pichika | H13: Srivijaya Pichika | I13: Srivijaya Pichika | J13: Sreedhar Nimmagadda | K13: =VLOOKUP(A13,'Employee detail'!$B$1:$F$220,5,0) -> PDC | M13: Billable | N13: 2350 | O13: 0.25531915
A14: 1013812 | B14: Jeshwant Kolan | C14: E2 | D14: JohnDeere | E14: TCI Staffing | F14: SAP FICO | G14: Srivijaya Pichika | H14: Nishanta Devadiga | I14: Srivijaya Pichika | J14: Shital Kupwade | K14: =VLOOKUP(A14,'Employee detail'!$B$1:$F$220,5,0) -> IT Finance | M14: Billable | N14: 1400 | O14: 0.43771429
A15: 1004516 | B15: Bhaskar Yellamanchili | C15: E3 | D15: JohnDeere | E15: TCI Staffing | F15: SAP HR | G15: Srivijaya Pichika | H15: Nishanta Devadiga | I15: Sharath Panaggamula | J15: Suresh Manthathi | K15: =VLOOKUP(A15,'Employee detail'!$B$1:$F$220,5,0) -> HCM | M15: Billable | N15: 1800 | O15: 0.49072222
A16: 1016969 | B16: Venkataraman J | C16: E3 | D16: JohnDeere | E16: TCI Staffing | F16: SAP ABAP HANA | G16: Srivijaya Pichika | H16: Srivijaya Pichika | I16: Srivijaya Pichika | J16: Felipe Engleman | K16: =VLOOKUP(A16,'Employee detail'!$B$1:$F$220,5,0) -> PDP | M16: Billable | N16: 1800 | O16: 0.30238889
A17: 1017777 | B17: Swati Patil | C17: E3 | D17: JohnDeere | E17: TCI Staffing | F17: SAP ABAP HANA | G17: Srivijaya Pichika | H17: Srivijaya Pichika | I17: Srivijaya Pichika | J17: Amit Koul | K17: =VLOOKUP(A17,'Employee detail'!$B$1:$F$220,5,0) -> CPS | M17: Billable | N17: 2100 | O17: 0.39047619
A18: 1601627 | B18: Sravani A | C18: C | D18: JohnDeere | E18: System Interoperability | F18: SAP ABAP HANA | G18: Srivijaya Pichika | H18: Abir Sarkar | I18: Srivijaya Pichika | J18: Mahesh Jayaraman | K18: =VLOOKUP(A18,'Employee detail'!$B$1:$F$220,5,0) -> MSP | M18: Billable | N18: 2100 | O18: 0.3015873
A19: 1601630 | B19: B Kiran Kumar | C19: C | D19: JohnDeere | E19: TCI Staffing | F19: SAP ABAP CRM | G19: Srivijaya Pichika | H19: Srivijaya Pichika | I19: Srivijaya Pichika | J19: Sreedhar Nimmagadda | K19: =VLOOKUP(A19,'Employee detail'!$B$1:$F$220,5,0) -> PDC | M19: Billable | N19: 2350 | O19: 0.25531915
A20: 1100051 | B20: Akash Bhutwani | C20: E2 | D20: JohnDeere | E20: TCI Staffing | F20: SAP ABAP HANA | G20: Srivijaya Pichika | H20: Nishanta Devadiga | I20: Srivijaya Pichika | J20: Dipesh Parekh | K20: =VLOOKUP(A20,'Employee detail'!$B$1:$F$220,5,0) -> IT Finance | M20: Billable | N20: 1700 | O20: 0.58811765
A21: 1601656 | B21: Nagam Rammohan | C21: C | D21: JohnDeere | E21: TCI Staffing | F21: SAP ABAP CRM | G21: Srivijaya Pichika | H21: Srivijaya Pichika | I21: Srivijaya Pichika | J21: Sreedhar Nimmagadda | K21: =VLOOKUP(A21,'Employee detail'!$B$1:$F$220,5,0) -> PDC | M21: Billable | N21: 2100 | O21: 0.22857143
... A35: 1602253 | B35: Tisha Haria | C35: C | D35: JohnDeere | E35: TCI Staffing | F35: SAP ABAP CRM | G35: Srivijaya Pichika | H35: Srivijaya Pichika | I35: Srivijaya Pichika | J35: Sreedhar Nimmagadda | K35: =VLOOKUP(A35,'Employee detail'!$B$1:$F$220,5,0) -> PDC | M35: Billable | N35: 2400 | O35: 0.31916667
A36: 1602284 | B36: Naga Jyothi Maddali | C36: C | D36: JohnDeere | E36: TCI Staffing | F36: SAP ABAP CRM | G36: Srivijaya Pichika | H36: Srivijaya Pichika | I36: Srivijaya Pichika | J36: Sreedhar Nimmagadda | K36: PDC | M36: Billable | N36: 2100 | O36: 0.29
J41: 49 | M41: 44 | N41: =J41+M41 -> 93 | O41: =N41/2 -> 46.5

Sheet for Kishore use
A1: Employee ID | B1: Employee Name | C1: Employee Status | D1: Employee Type | E1: Designation | F1: IRM | G1: Parent BG | H1: Parent BU | I1: Competency | J1: Allocation Type | K1: Sub Allocation Type | L1: Allocation % | M1: Hourly Bill Rates | N1: Conversion Factor | O1: Run Rate (Monthly) | P1: CTC | Q1: OH | R1: CTC(U) | S1: OH(U) | T1: Emp Cost | U1: Profit | V1: Profit% | W1: Project Name | X1: Group | Y1: Project Manager | Z1: Delivery Manager | AA1: Project BUHSSUH | AB1: Project BGHSSGH | AC1: Project BG | AD1: Project BU | AE1: Project Hour Day | AF1: Project Currency
A2: 1601783 | B2: Abhishek Premsing Jadhav | C2: Active | D2: Contractual | E2: Contractor | F2: Rajesh Radhakrishnan Nair | G2: BG5 | H2: BG5-BU11 | I2: Microsoft | J2: Billable | K2: Billable | L2: 100 | M2: 1800 | N2: 0.012195122 | O2: =(L2/100)*M2*N2*(20*AE2) -> 3951.2195 | P2: 2430000 | Q2: 300000 | R2: =IFERROR(P2*(L2/100),"-") -> 2430000 | S2: =IFERROR(Q2*(L2/100),"-") -> 300000 | T2: =IFERROR((R2+S2)/(86*12),"-") -> 2645.3488 | U2: =O2-T2 -> 1305.8707 | V2: =U2/O2 -> 0.33049813 | W2: JD-TCI-BG4-BU4-CAP | X2: CAP | Y2: Rajesh Radhakrishnan Nair | Z2: Seshakishore Kumar Kollipara | AA2: Shailendra Gupta | AB2: Arun Kumar Mishra | AC2: BG4 | AD2: BG4-BU4 | AE2: 9 | AF2: INR
A3: 1102379 | B3: Pankaj Kumar Singh | C3: Active | D3: Permanent | E3: Sr. Software Engineer | F3: Rajesh Radhakrishnan Nair | G3: BG4 | H3: BG4-BU4 | I3: Java | J3: Billable | K3: Billable | L3: 100 | M3: 1700 | N3: 0.012195122 | O3: =(L3/100)*M3*N3*(20*AE3) -> 3731.7073 | P3: 1389395 | Q3: 300000 | R3: =IFERROR(P3*(L3/100),"-") -> 1389395 | S3: =IFERROR(Q3*(L3/100),"-") -> 300000 | T3: =IFERROR((R3+S3)/(86*12),"-") -> 1637.0107 | U3: =O3-T3 -> 2094.6966 | V3: =U3/O3 -> 0.56132393 | W3: JD-TCI-BG4-BU4-CAP | X3: CAP | Y3: Rajesh Radhakrishnan Nair | Z3: Seshakishore Kumar Kollipara | AA3: Shailendra Gupta | AB3: Arun Kumar Mishra | AC3: BG4 | AD3: BG4-BU4 | AE3: 9 | AF3: INR
A4: 1102381 | B4: Lakshya Sharma | C4: Active | D4: Permanent | E4: Sr. Software Engineer | F4: Rajesh Radhakrishnan Nair | G4: BG4 | H4: BG4-BU4 | I4: Mobility | J4: Billable | K4: Billable | L4: 100 | M4: 1400 | N4: 0.012195122 | O4: =(L4/100)*M4*N4*(20*AE4) -> 3073.1707 | P4: 1389395 | Q4: 300000 | R4: =IFERROR(P4*(L4/100),"-") -> 1389395 | S4: =IFERROR(Q4*(L4/100),"-") -> 300000 | T4: =IFERROR((R4+S4)/(86*12),"-") -> 1637.0107 | U4: =O4-T4 -> 1436.16 | V4: =U4/O4 -> 0.46732192 | W4: JD-TCI-BG4-BU4-CAP | X4: CAP | Y4: Rajesh Radhakrishnan Nair | Z4: Seshakishore Kumar Kollipara | AA4: Shailendra Gupta | AB4: Arun Kumar Mishra | AC4: BG4 | AD4: BG4-BU4 | AE4: 9 | AF4: INR
A5: 1014127 | B5: Mayuri Nandkishorji Mundada | C5: Active | D5: Permanent | E5: Software Engineer | F5: Rajesh Radhakrishnan Nair | G5: BG4 | H5: BG4-BU4 | I5: Java | J5: Billable | K5: Billable | L5: 100 | M5: 1400 | N5: 0.012195122 | O5: =(L5/100)*M5*N5*(20*AE5) -> 3073.1707 | P5: 487704 | Q5: 300000 | R5: =IFERROR(P5*(L5/100),"-") -> 487704 | S5: =IFERROR(Q5*(L5/100),"-") -> 300000 | T5: =IFERROR((R5+S5)/(86*12),"-") -> 763.27907 | U5: =O5-T5 -> 2309.8917 | V5: =U5/O5 -> 0.75163141 | W5: JD-TCI-BG4-BU4-CAP | X5: CAP | Y5: Rajesh Radhakrishnan Nair | Z5: Seshakishore Kumar Kollipara | AA5: Shailendra Gupta | AB5: Arun Kumar Mishra | AC5: BG4 | AD5: BG4-BU4 | AE5: 9 | AF5: INR
A6: 1016125 | B6: Ashwini Jagannath Lohar | C6: Active | D6: Permanent | E6: Software Engineer | F6: Rajesh Radhakrishnan Nair | G6: BG4 | H6: BG4-BU4 | I6: Java | J6: Billable | K6: Billable | L6: 100 | M6: 1400 | N6: 0.012195122 | O6: =(L6/100)*M6*N6*(20*AE6) -> 3073.1707 | P6: 695604 | Q6: 300000 | R6: =IFERROR(P6*(L6/100),"-") -> 695604 | S6: =IFERROR(Q6*(L6/100),"-") -> 300000 | T6: =IFERROR((R6+S6)/(86*12),"-") -> 964.73256 | U6: =O6-T6 -> 2108.4382 | V6: =U6/O6 -> 0.68607909 | W6: JD-TCI-BG4-BU4-CAP | X6: CAP | Y6: Rajesh Radhakrishnan Nair | Z6: Seshakishore Kumar Kollipara | AA6: Shailendra Gupta | AB6: Arun Kumar Mishra | AC6: BG4 | AD6: BG4-BU4 | AE6: 9 | AF6: INR
A7: 1017632 | B7: Ajinkya Sharad Mane | C7: Active | D7: Permanent | E7: UI Specialist | F7: Rajesh Radhakrishnan Nair | G7: BG5 | H7: BG5-BU1 | I7: User Interface (UI) | J7: Billable | K7: Billable | L7: 100 | M7: 1400 | N7: 0.012195122 | O7: =(L7/100)*M7*N7*(20*AE7) -> 3073.1707 | P7: 884508 | Q7: 300000 | R7: =IFERROR(P7*(L7/100),"-") -> 884508 | S7: =IFERROR(Q7*(L7/100),"-") -> 300000 | T7: =IFERROR((R7+S7)/(86*12),"-") -> 1147.7791 | U7: =O7-T7 -> 1925.3917 | V7: =U7/O7 -> 0.62651633 | W7: JD-TCI-BG4-BU4-CAP | X7: CAP | Y7: Rajesh Radhakrishnan Nair | Z7: Seshakishore Kumar Kollipara | AA7: Shailendra Gupta | AB7: Arun Kumar Mishra | AC7: BG4 | AD7: BG4-BU4 | AE7: 9 | AF7: INR
A8: 1016107 | B8: Shekhar Kumar Jha | C8: Active | D8: Permanent | E8: Sr. Software Engineer | F8: Rajesh Radhakrishnan Nair | G8: BG4 | H8: BG4-BU4 | I8: Java | J8: Billable | K8: Billable | L8: 100 | M8: 1400 | N8: 0.012195122 | O8: =(L8/100)*M8*N8*(20*AE8) -> 3073.1707 | P8: 956304 | Q8: 300000 | R8: =IFERROR(P8*(L8/100),"-") -> 956304 | S8: =IFERROR(Q8*(L8/100),"-") -> 300000 | T8: =IFERROR((R8+S8)/(86*12),"-") -> 1217.3488 | U8: =O8-T8 -> 1855.8219 | V8: =U8/O8 -> 0.60387855 | W8: JD-TCI-BG4-BU4-CAP | X8: CAP | Y8: Rajesh Radhakrishnan Nair | Z8: Seshakishore Kumar Kollipara | AA8: Shailendra Gupta | AB8: Arun Kumar Mishra | AC8: BG4 | AD8: BG4-BU4 | AE8: 9 | AF8: INR
A9: 1011367 | B9: Avinash Kumar Singh | C9: Active | D9: Permanent | E9: Software Engineer | F9: Rajesh Radhakrishnan Nair | G9: BG5 | H9: BG5-BU11 | I9: Microsoft | J9: Billable | K9: Billable | L9: 100 | M9: 1400 | N9: 0.012195122 | O9: =(L9/100)*M9*N9*(20*AE9) -> 3073.1707 | P9: 1100004 | Q9: 300000 | R9: =IFERROR(P9*(L9/100),"-") -> 1100004 | S9: =IFERROR(Q9*(L9/100),"-") -> 300000 | T9: =IFERROR((R9+S9)/(86*12),"-") -> 1356.593 | U9: =O9-T9 -> 1716.5777 | V9: =U9/O9 -> 0.55856894 | W9: JD-TCI-BG4-BU4-CAP | X9: CAP | Y9: Rajesh Radhakrishnan Nair | Z9: Seshakishore Kumar Kollipara | AA9: Shailendra Gupta | AB9: Arun Kumar Mishra | AC9: BG4 | AD9: BG4-BU4 | AE9: 9 | AF9: INR
A10: 1100645 | B10: Ankita Ajay Chaudhari | C10: Active | D10: Permanent | E10: Associate Consultant | F10: Rajesh Radhakrishnan Nair | G10: BG5 | H10: BG5-BU11 | I10: Microsoft | J10: Billable | K10: Billable | L10: 100 | M10: 1400 | N10: 0.012195122 | O10: =(L10/100)*M10*N10*(20*AE10) -> 3073.1707 | P10: 1100004 | Q10: 300000 | R10: =IFERROR(P10*(L10/100),"-") -> 1100004 | S10: =IFERROR(Q10*(L10/100),"-") -> 300000 | T10: =IFERROR((R10+S10)/(86*12),"-") -> 1356.593 | U10: =O10-T10 -> 1716.5777 | V10: =U10/O10 -> 0.55856894 | W10: JD-TCI-BG4-BU4-CAP | X10: CAP | Y10: Rajesh Radhakrishnan Nair | Z10: Seshakishore Kumar Kollipara | AA10: Shailendra Gupta | AB10: Arun Kumar Mishra | AC10: BG4 | AD10: BG4-BU4 | AE10: 9 | AF10: INR
A11: 1017087 | B11: Shubham Sanjay Deshpande | C11: Active | D11: Permanent | E11: Sr. Software Engineer | F11: Rajesh Radhakrishnan Nair | G11: BG4 | H11: BG4-BU4 | I11: Java | J11: Billable | K11: Billable | L11: 100 | M11: 1200 | N11: 0.012195122 | O11: =(L11/100)*M11*N11*(20*AE11) -> 2634.1463 | P11: 1146804 | Q11: 300000 | R11: =IFERROR(P11*(L11/100),"-") -> 1146804 | S11: =IFERROR(Q11*(L11/100),"-") -> 300000 | T11: =IFERROR((R11+S11)/(86*12),"-") -> 1401.9419 | U11: =O11-T11 -> 1232.2045 | V11: =U11/O11 -> 0.46778133 | W11: JD-TCI-BG4-BU4-CAP | X11: CAP | Y11: Rajesh Radhakrishnan Nair | Z11: Seshakishore Kumar Kollipara | AA11: Shailendra Gupta | AB11: Arun Kumar Mishra | AC11: BG4 | AD11: BG4-BU4 | AE11: 9 | AF11: INR
A12: 1100745 | B12: Pushpak Satish Bhambar | C12: Active | D12: Permanent | E12: Sr. Software Engineer | F12: Rajesh Radhakrishnan Nair | G12: BG4 | H12: BG4-BU4 | I12: Java | J12: Billable | K12: Billable | L12: 100 | M12: 1200 | N12: 0.012195122 | O12: =(L12/100)*M12*N12*(20*AE12) -> 2634.1463 | P12: 1200000 | Q12: 300000 | R12: =IFERROR(P12*(L12/100),"-") -> 1200000 | S12: =IFERROR(Q12*(L12/100),"-") -> 300000 | T12: =IFERROR((R12+S12)/(86*12),"-") -> 1453.4884 | U12: =O12-T12 -> 1180.658 | V12: =U12/O12 -> 0.44821275 | W12: JD-TCI-BG4-BU4-CAP | X12: CAP | Y12: Rajesh Radhakrishnan Nair | Z12: Seshakishore Kumar Kollipara | AA12: Shailendra Gupta | AB12: Arun Kumar Mishra | AC12: BG4 | AD12: BG4-BU4 | AE12: 9 | AF12: INR
A13: 1015565 | B13: Mithun Jayswal | C13: Active | D13: Permanent | E13: Sr. Software Engineer | F13: Rajesh Radhakrishnan Nair | G13: BG4 | H13: BG4-BU4 | I13: Mainframe | J13: Billable | K13: Billable | L13: 100 | M13: 1700 | N13: 0.012195122 | O13: =(L13/100)*M13*N13*(20*AE13) -> 3731.7073 | P13: 1201008 | Q13: 300000 | R13: =IFERROR(P13*(L13/100),"-") -> 1201008 | S13: =IFERROR(Q13*(L13/100),"-") -> 300000 | T13: =IFERROR((R13+S13)/(86*12),"-") -> 1454.4651 | U13: =O13-T13 -> 2277.2422 | V13: =U13/O13 -> 0.61024137 | W13: JD-TCI-BG4-BU4-CAP | X13: CAP | Y13: Rajesh Radhakrishnan Nair | Z13: Seshakishore Kumar Kollipara | AA13: Shailendra Gupta | AB13: Arun Kumar Mishra | AC13: BG4 | AD13: BG4-BU4 | AE13: 9 | AF13: INR
... A83: 1014173 | B83: Manuja Ashok Kshirsagar | C83: Active | D83: Permanent | E83: Project Manager | F83: Rajesh Radhakrishnan Nair | G83: BG5 | H83: BG5-BU1 | I83: Agile Consulting | J83: Billable | K83: Billable | L83: 100 | M83: 1800 | N83: 0.012195122 | O83: =(L83/100)*M83*N83*(20*AE83) -> 3951.2195 | P83: 2785000 | Q83: 300000 | R83: =IFERROR(P83*(L83/100),"-") -> 2785000 | S83: =IFERROR(Q83*(L83/100),"-") -> 300000 | T83: =IFERROR((R83+S83)/(86*12),"-") -> 2989.3411 | U83: =O83-T83 -> 961.87843 | V83: =U83/O83 -> 0.24343837 | W83: JD-TCI-BG4-BU4-CPS | X83: CPS | Y83: Nilesh W Bansodkar | Z83: Seshakishore Kumar Kollipara | AA83: Shailendra Gupta | AB83: Arun Kumar Mishra | AC83: BG4 | AD83: BG4-BU4 | AE83: 9 | AF83: INR
A84: 1017777 | B84: Swati Patil | I84: SAP | V84: 0.39047619 | X84: CPS
A85: 1101854 | B85: Harika Meka | I85: SAP | V85: 0.46428571 | X85: CPS
A86: 1101676 | B86: Priyanshu Chouhan | I86: SAP | V86: 0.46428571 | X86: CPS
A87: 1017094 | B87: Pravin Arvind Deshpande | C87: Active | D87: Permanent | E87: Sr. Software Engineer | F87: Nilesh W Bansodkar | G87: BG4 | H87: BG4-BU4 | I87: Content Management System (CMS) | J87: Billable | K87: Billable | L87: 100 | M87: 880 | N87: 0.012195122 | O87: =(L87/100)*M87*N87*(20*AE87) -> 1931.7073 | P87: 812508 | Q87: 300000 | R87: =IFERROR(P87*(L87/100),"-") -> 812508 | S87: =IFERROR(Q87*(L87/100),"-") -> 300000 | T87: =IFERROR((R87+S87)/(86*12),"-") -> 1078.0116 | U87: =O87-T87 -> 853.69569 | V87: =U87/O87 -> 0.44193842 | W87: JD-TCI-BG4-BU4-CPSS | X87: CPSS | Y87: Nilesh W Bansodkar | Z87: Seshakishore Kumar Kollipara | AA87: Shailendra Gupta | AB87: Arun Kumar Mishra | AC87: BG4 | AD87: BG4-BU4 | AE87: 9 | AF87: INR
A88: 1012750 | B88: Jeet Kumar Patidar | C88: Active | D88: Permanent | E88: Software Engineer | F88: Manish Gupta | G88: BG4 | H88: BG4-BU4 | I88: Java | J88: Billable | K88: Billable | L88: 100 | M88: 1400 | N88: 0.012195122 | O88: =(L88/100)*M88*N88*(20*AE88) -> 3073.1707 | P88: 862908 | Q88: 300000 | R88: =IFERROR(P88*(L88/100),"-") -> 862908 | S88: =IFERROR(Q88*(L88/100),"-") -> 300000 | T88: =IFERROR((R88+S88)/(86*12),"-") -> 1126.8488 | U88: =O88-T88 -> 1946.3219 | V88: =U88/O88 -> 0.63332697 | W88: JD-TCI-BG4-BU4-D&A | X88: D&A | Y88: Nilesh W Bansodkar | Z88: Seshakishore Kumar Kollipara | AA88: Shailendra Gupta | AB88: Arun Kumar Mishra | AC88: BG4 | AD88: BG4-BU4 | AE88: 9 | AF88: INR
A89: 1102109 | B89: Sradha Suman Dash | C89: Active | D89: Permanent | E89: Sr. Software Engineer | F89: Nilesh W Bansodkar | G89: BG5 | H89: BG5-BU12 | I89: Data & Analytics | J89: Billable | K89: Billable | L89: 100 | M89: 1700 | N89: 0.012195122 | O89: =(L89/100)*M89*N89*(20*AE89) -> 3731.7073 | P89: 1100004 | Q89: 300000 | R89: =IFERROR(P89*(L89/100),"-") -> 1100004 | S89: =IFERROR(Q89*(L89/100),"-") -> 300000 | T89: =IFERROR((R89+S89)/(86*12),"-") -> 1356.593 | U89: =O89-T89 -> 2375.1143 | V89: =U89/O89 -> 0.63646854 | W89: JD-TCI-BG4-BU4-D&A | X89: D&A | Y89: Nilesh W Bansodkar | Z89: Seshakishore Kumar Kollipara | AA89: Shailendra Gupta | AB89: Arun Kumar Mishra | AC89: BG4 | AD89: BG4-BU4 | AE89: 9 | AF89: INR
A90: 1016906 | B90: Jalasutram Durga Prasad | C90: Active | D90: Permanent | E90: Sr. Software Engineer | F90: Nilesh W Bansodkar | G90: BG4 | H90: BG4-BU4 | I90: Mainframe | J90: Billable | K90: Billable | L90: 100 | M90: 1500 | N90: 0.012195122 | O90: =(L90/100)*M90*N90*(20*AE90) -> 3292.6829 | P90: 1264008 | Q90: 300000 | R90: =IFERROR(P90*(L90/100),"-") -> 1264008 | S90: =IFERROR(Q90*(L90/100),"-") -> 300000 | T90: =IFERROR((R90+S90)/(86*12),"-") -> 1515.5116 | U90: =O90-T90 -> 1777.1713 | V90: =U90/O90 -> 0.53973351 | W90: JD-TCI-BG4-BU4-D&A | X90: D&A | Y90: Nilesh W Bansodkar | Z90: Seshakishore Kumar Kollipara | AA90: Shailendra Gupta | AB90: Arun Kumar Mishra | AC90: BG4 | AD90: BG4-BU4 | AE90: 9 | AF90: INR
A91: 1102035 | B91: Aniket Krushnat Gaikwad | C91: Active | D91: Permanent | E91: Sr. Software Engineer | F91: Nilesh W Bansodkar | G91: BG4 | H91: BG4-BU4 | I91: Java | J91: Billable | K91: Billable | L91: 100 | M91: 1200 | N91: 0.012195122 | O91: =(L91/100)*M91*N91*(20*AE91) -> 2634.1463 | P91: 1350000 | Q91: 300000 | R91: =IFERROR(P91*(L91/100),"-") -> 1350000 | S91: =IFERROR(Q91*(L91/100),"-") -> 300000 | T91: =IFERROR((R91+S91)/(86*12),"-") -> 1598.8372 | U91: =O91-T91 -> 1035.3091 | V91: =U91/O91 -> 0.39303402 | W91: JD-TCI-BG4-BU4-D&A | X91: D&A | Y91: Nilesh W Bansodkar | Z91: Seshakishore Kumar Kollipara | AA91: Shailendra Gupta | AB91: Arun Kumar Mishra | AC91: BG4 | AD91: BG4-BU4 | AE91: 9 | AF91: INR
A92: 1100468 | B92: Pooja Ashok Ambawle | C92: Active | D92: Permanent | E92: Sr. Software Engineer | F92: Nilesh W Bansodkar | G92: BG4 | H92: BG4-BU4 | I92: Mainframe | J92: Billable | K92: Billable | L92: 100 | M92: 1800 | N92: 0.012195122 | O92: =(L92/100)*M92*N92*(20*AE92) -> 3951.2195 | P92: 1500000 | Q92: 300000 | R92: =IFERROR(P92*(L92/100),"-") -> 1500000 | S92: =IFERROR(Q92*(L92/100),"-") -> 300000 | T92: =IFERROR((R92+S92)/(86*12),"-") -> 1744.186 | U92: =O92-T92 -> 2207.0335 | V92: =U92/O92 -> 0.5585702 | W92: JD-TCI-BG4-BU4-D&A | X92: D&A | Y92: Nilesh W Bansodkar | Z92: Seshakishore Kumar Kollipara | AA92: Shailendra Gupta | AB92: Arun Kumar Mishra | AC92: BG4 | AD92: BG4-BU4 | AE92: 9 | AF92: INR
A93: 1101688 | B93: Shantanu Mithilesh Moraskr | C93: Active | D93: Permanent | E93: Sr. Software Engineer | F93: Nilesh W Bansodkar | G93: BG4 | H93: BG4-BU4 | I93: Java | J93: Billable | K93: Billable | L93: 100 | M93: 1700 | N93: 0.012195122 | O93: =(L93/100)*M93*N93*(20*AE93) -> 3731.7073 | P93: 1500000 | Q93: 300000 | R93: =IFERROR(P93*(L93/100),"-") -> 1500000 | S93: =IFERROR(Q93*(L93/100),"-") -> 300000 | T93: =IFERROR((R93+S93)/(86*12),"-") -> 1744.186 | U93: =O93-T93 -> 1987.5213 | V93: =U93/O93 -> 0.53260374 | W93: JD-TCI-BG4-BU4-D&A | X93: D&A | Y93: Nilesh W Bansodkar | Z93: Seshakishore Kumar Kollipara | AA93: Shailendra Gupta | AB93: Arun Kumar Mishra | AC93: BG4 | AD93: BG4-BU4 | AE93: 9 | AF93: INR
A94: 1017691 | B94: Deepa Basavaraj Patil | C94: Active | D94: Permanent | E94: UI Specialist | F94: Nilesh W Bansodkar | G94: BG5 | H94: BG5-BU1 | I94: User Interface (UI) | J94: Billable | K94: Billable | L94: 100 | M94: 1800 | N94: 0.012195122 | O94: =(L94/100)*M94*N94*(20*AE94) -> 3951.2195 | P94: 1561800 | Q94: 300000 | R94: =IFERROR(P94*(L94/100),"-") -> 1561800 | S94: =IFERROR(Q94*(L94/100),"-") -> 300000 | T94: =IFERROR((R94+S94)/(86*12),"-") -> 1804.0698 | U94: =O94-T94 -> 2147.1497 | V94: =U94/O94 -> 0.54341444 | W94: JD-TCI-BG4-BU4-D&A | X94: D&A | Y94: Nilesh W Bansodkar | Z94: Seshakishore Kumar Kollipara | AA94: Shailendra Gupta | AB94: Arun Kumar Mishra | AC94: BG4 | AD94: BG4-BU4 | AE94: 9 | AF94: INR
A95: 1100163 | B95: Akash Sahebrao Kadhane | C95: Active | D95: Permanent | E95: Sr. Software Engineer | F95: Nilesh W Bansodkar | G95: BG5 | H95: BG5-BU12 | I95: Data & Analytics | J95: Billable | K95: Billable | L95: 100 | M95: 2100 | N95: 0.012195122 | O95: =(L95/100)*M95*N95*(20*AE95) -> 4609.7561 | P95: 1650000 | Q95: 300000 | R95: =IFERROR(P95*(L95/100),"-") -> 1650000 | S95: =IFERROR(Q95*(L95/100),"-") -> 300000 | T95: =IFERROR((R95+S95)/(86*12),"-") -> 1889.5349 | U95: =O95-T95 -> 2720.2212 | V95: =U95/O95 -> 0.5901009 | W95: JD-TCI-BG4-BU4-D&A | X95: D&A | Y95: Nilesh W Bansodkar | Z95: Seshakishore Kumar Kollipara | AA95: Shailendra Gupta | AB95: Arun Kumar Mishra | AC95: BG4 | AD95: BG4-BU4 | AE95: 9 | AF95: INR
A96: 1102115 | B96: Sneha Balaram Yadav | C96: Active | D96: Permanent | E96: Sr. Software Engineer | F96: Nilesh W Bansodkar | G96: BG5 | H96: BG5-BU12 | I96: Data & Analytics | J96: Billable | K96: Billable | L96: 100 | M96: 1700 | N96: 0.012195122 | O96: =(L96/100)*M96*N96*(20*AE96) -> 3731.7073 | P96: 1800000 | Q96: 300000 | R96: =IFERROR(P96*(L96/100),"-") -> 1800000 | S96: =IFERROR(Q96*(L96/100),"-") -> 300000 | T96: =IFERROR((R96+S96)/(86*12),"-") -> 2034.8837 | U96: =O96-T96 -> 1696.8236 | V96: =U96/O96 -> 0.45470436 | W96: JD-TCI-BG4-BU4-D&A | X96: D&A | Y96: Nilesh W Bansodkar | Z96: Seshakishore Kumar Kollipara | AA96: Shailendra Gupta | AB96: Arun Kumar Mishra | AC96: BG4 | AD96: BG4-BU4 | AE96: 9 | AF96: INR
A97: 1100076 | B97: Rahul Manohar Mhakave | C97: Active | D97: Permanent | E97: Sr. Software Engineer | F97: Nilesh W Bansodkar | G97: BG5 | H97: BG5-BU12 | I97: Data & Analytics | J97: Billable | K97: Billable | L97: 100 | M97: 2100 | N97: 0.012195122 | O97: =(L97/100)*M97*N97*(20*AE97) -> 4609.7561 | P97: 1850004 | Q97: 300000 | R97: =IFERROR(P97*(L97/100),"-") -> 1850004 | S97: =IFERROR(Q97*(L97/100),"-") -> 300000 | T97: =IFERROR((R97+S97)/(86*12),"-") -> 2083.3372 | U97: =O97-T97 -> 2526.4189 | V97: =U97/O97 -> 0.54805912 | W97: JD-TCI-BG4-BU4-D&A | X97: D&A | Y97: Nilesh W Bansodkar | Z97: Seshakishore Kumar Kollipara | AA97: Shailendra Gupta | AB97: Arun Kumar Mishra | AC97: BG4 | AD97: BG4-BU4 | AE97: 9 | AF97: INR
A98: 1000110 | B98: Jai Kumar Gadoeya | C98: Active | D98: Permanent | E98: Sr. Tech Lead | F98: Manish Gupta | G98: BG4 | H98: BG4-BU4 | I98: Java | J98: Billable | K98: Billable | L98: 100 | M98: 2100 | N98: 0.012195122 | O98: =(L98/100)*M98*N98*(20*AE98) -> 4609.7561 | P98: 2500000 | Q98: 300000 | R98: =IFERROR(P98*(L98/100),"-") -> 2500000 | S98: =IFERROR(Q98*(L98/100),"-") -> 300000 | T98: =IFERROR((R98+S98)/(86*12),"-") -> 2713.1783 | U98: =O98-T98 -> 1896.5778 | V98: =U98/O98 -> 0.41142693 | W98: JD-TCI-BG4-BU4-D&A | X98: D&A | Y98: Nilesh W Bansodkar | Z98: Seshakishore Kumar Kollipara | AA98: Shailendra Gupta | AB98: Arun Kumar Mishra | AC98: BG4 | AD98: BG4-BU4 | AE98: 9 | AF98: INR
... A109: 1009357 | B109: Harshal Ketan Patil | C109: Active | D109: Permanent | E109: Module Lead | F109: Nilesh W Bansodkar | G109: BG4 | H109: BG4-BU4 | I109: Java | J109: Billable | K109: Billable | L109: 100 | M109: 1800 | N109: 0.012195122 | O109: =(L109/100)*M109*N109*(20*AE109) -> 3951.2195 | P109: 1550308 | Q109: 300000 | R109: =IFERROR(P109*(L109/100),"-") -> 1550308 | S109: =IFERROR(Q109*(L109/100),"-") -> 300000 | T109: =IFERROR((R109+S109)/(86*12),"-") -> 1792.9341 | U109: =O109-T109 -> 2158.2854 | V109: =U109/O109 -> 0.54623273 | W109: JD-TCI-BG4-BU4-Foundry | X109: Foundry | Y109: Nilesh W Bansodkar | Z109: Seshakishore Kumar Kollipara | AA109: Shailendra Gupta | AB109: Arun Kumar Mishra | AC109: BG4 | AD109: BG4-BU4 | AE109: 9 | AF109: INR
A110: 1009797 | B110: Vivek Anaskar | I110: SAP | V110: 0.30933333 | X110: HCM
A111: 1005201 | B111: Vijaya Ganapa | I111: SAP | V111: 0.54711111 | X111: HCM
A112: 1004516 | B112: Bhaskar Yellamanchili | I112: SAP | V112: 0.49072222 | X112: HCM
A113: 1102205 | B113: Shivam Gopal Kayarkar | C113: Active | D113: Permanent | E113: Consultant | F113: Nilesh W Bansodkar | G113: BG5 | H113: BG5-BU15 | I113: ServiceNow | J113: Billable | K113: Billable | L113: 100 | M113: 1700 | N113: 0.012195122 | O113: =(L113/100)*M113*N113*(20*AE113) -> 3731.7073 | P113: 1389395 | Q113: 300000 | R113: =IFERROR(P113*(L113/100),"-") -> 1389395 | S113: =IFERROR(Q113*(L113/100),"-") -> 300000 | T113: =IFERROR((R113+S113)/(86*12),"-") -> 1637.0107 | U113: =O113-T113 -> 2094.6966 | V113: =U113/O113 -> 0.56132393 | W113: JD-TCI-BG4-BU4-I&O | X113: I&O | Y113: Nilesh W Bansodkar | Z113: Seshakishore Kumar Kollipara | AA113: Shailendra Gupta | AB113: Arun Kumar Mishra | AC113: BG4 | AD113: BG4-BU4 | AE113: 9 | AF113: INR
A114: 1100814 | B114: Kale Laxmikant Vitthalrao | C114: Active | D114: Permanent | E114: Software Engineer | F114: Nilesh W Bansodkar | G114: BG5 | H114: BG5-BU12 | I114: Data & Analytics | J114: Billable | K114: Billable | L114: 100 | M114: 1200 | N114: 0.012195122 | O114: =(L114/100)*M114*N114*(20*AE114) -> 2634.1463 | P114: 1050000 | Q114: 300000 | R114: =IFERROR(P114*(L114/100),"-") -> 1050000 | S114: =IFERROR(Q114*(L114/100),"-") -> 300000 | T114: =IFERROR((R114+S114)/(86*12),"-") -> 1308.1395 | U114: =O114-T114 -> 1326.0068 | V114: =U114/O114 -> 0.50339147 | W114: JD-TCI-BG4-BU4-I&O | X114: I&O | Y114: Nilesh W Bansodkar | Z114: Seshakishore Kumar Kollipara | AA114: Shailendra Gupta | AB114: Arun Kumar Mishra | AC114: BG4 | AD114: BG4-BU4 | AE114: 9 | AF114: INR
A115: 1007362 | B115: Anwar Bashirahmad Kudle | C115: Active | D115: Permanent | E115: Sr. Consultant | F115: Nilesh W Bansodkar | G115: BG5 | H115: BG5-BU9 | I115: Core-Infra | J115: Billable | K115: Billable | L115: 100 | M115: 1700 | N115: 0.012195122 | O115: =(L115/100)*M115*N115*(20*AE115) -> 3731.7073 | P115: 1891000 | Q115: 300000 | R115: =IFERROR(P115*(L115/100),"-") -> 1891000 | S115: =IFERROR(Q115*(L115/100),"-") -> 300000 | T115: =IFERROR((R115+S115)/(86*12),"-") -> 2123.062 | U115: =O115-T115 -> 1608.6453 | V115: =U115/O115 -> 0.43107488 | W115: JD-TCI-BG4-BU4-I&O | X115: I&O | Y115: Nilesh W Bansodkar | Z115: Seshakishore Kumar Kollipara | AA115: Shailendra Gupta | AB115: Arun Kumar Mishra | AC115: BG4 | AD115: BG4-BU4 | AE115: 9 | AF115: INR
A116: 1008531 | B116: Prachi Sanmesh Kale | C116: Active | D116: Permanent | E116: Tech Lead | F116: Nilesh W Bansodkar | G116: BG4 | H116: BG4-BU4 | I116: Java | J116: Billable | K116: Billable | L116: 100 | M116: 1800 | N116: 0.012195122 | O116: =(L116/100)*M116*N116*(20*AE116) -> 3951.2195 | P116: 1948508 | Q116: 300000 | R116: =IFERROR(P116*(L116/100),"-") -> 1948508 | S116: =IFERROR(Q116*(L116/100),"-") -> 300000 | T116: =IFERROR((R116+S116)/(86*12),"-") -> 2178.7868 | U116: =O116-T116 -> 1772.4327 | V116: =U116/O116 -> 0.44857864 | W116: JD-TCI-BG4-BU4-I&O | X116: I&O | Y116: Nilesh W Bansodkar | Z116: Seshakishore Kumar Kollipara | AA116: Shailendra Gupta | AB116: Arun Kumar Mishra | AC116: BG4 | AD116: BG4-BU4 | AE116: 9 | AF116: INR
A117: 1100752 | B117: Priti Subhash Naik | C117: Active | D117: Permanent | E117: Consultant | F117: Nilesh W Bansodkar | G117: BG5 | H117: BG5-BU15 | I117: ServiceNow | J117: Billable | K117: Billable | L117: 100 | M117: 1800 | N117: 0.012195122 | O117: =(L117/100)*M117*N117*(20*AE117) -> 3951.2195 | P117: 2100000 | Q117: 300000 | R117: =IFERROR(P117*(L117/100),"-") -> 2100000 | S117: =IFERROR(Q117*(L117/100),"-") -> 300000 | T117: =IFERROR((R117+S117)/(86*12),"-") -> 2325.5814 | U117: =O117-T117 -> 1625.6381 | V117: =U117/O117 -> 0.41142693 | W117: JD-TCI-BG4-BU4-I&O | X117: I&O | Y117: Nilesh W Bansodkar | Z117: Seshakishore Kumar Kollipara | AA117: Shailendra Gupta | AB117: Arun Kumar Mishra | AC117: BG4 | AD117: BG4-BU4 | AE117: 9 | AF117: INR
A118: 1101611 | B118: Prabin Kumar Baitharu | C118: Active | D118: Permanent | E118: Sr. Consultant | F118: Nilesh W Bansodkar | G118: BG5 | H118: BG5-BU15 | I118: ServiceNow | J118: Billable | K118: Billable | L118: 100 | M118: 2100 | N118: 0.012195122 | O118: =(L118/100)*M118*N118*(20*AE118) -> 4609.7561 | P118: 2800000 | Q118: 300000 | R118: =IFERROR(P118*(L118/100),"-") -> 2800000 | S118: =IFERROR(Q118*(L118/100),"-") -> 300000 | T118: =IFERROR((R118+S118)/(86*12),"-") -> 3003.876 | U118: =O118-T118 -> 1605.8801 | V118: =U118/O118 -> 0.34836553 | W118: JD-TCI-BG4-BU4-I&O | X118: I&O | Y118: Nilesh W Bansodkar | Z118: Seshakishore Kumar Kollipara | AA118: Shailendra Gupta | AB118: Arun Kumar Mishra | AC118: BG4 | AD118: BG4-BU4 | AE118: 9 | AF118: INR
A119: 1100287 | B119: Shardullya Vikram Singh | C119: Active | D119: Permanent | E119: Sr. Software Engineer | F119: Rajesh Radhakrishnan Nair | G119: BG4 | H119: BG4-BU4 | I119: Mobility | J119: Billable | K119: Billable | L119: 100 | M119: 1400 | N119: 0.012195122 | O119: =(L119/100)*M119*N119*(20*AE119) -> 3073.1707 | P119: 1326108 | Q119: 300000 | R119: =IFERROR(P119*(L119/100),"-") -> 1326108 | S119: =IFERROR(Q119*(L119/100),"-") -> 300000 | T119: =IFERROR((R119+S119)/(86*12),"-") -> 1575.686 | U119: =O119-T119 -> 1497.4847 | V119: =U119/O119 -> 0.48727676 | W119: JD-TCI-BG4-BU4-ISG | X119: ISG | Y119: Rajesh Radhakrishnan Nair | Z119: Seshakishore Kumar Kollipara | AA119: Shailendra Gupta | AB119: Arun Kumar Mishra | AC119: BG4 | AD119: BG4-BU4 | AE119: 9 | AF119: INR
A120: 1100284 | B120: Omkar Vaibhav Shinde | C120: Active | D120: Permanent | E120: Sr. Software Engineer | F120: Rajesh Radhakrishnan Nair | G120: BG4 | H120: BG4-BU4 | I120: Mobility | J120: Billable | K120: Billable | L120: 100 | M120: 1400 | N120: 0.012195122 | O120: =(L120/100)*M120*N120*(20*AE120) -> 3073.1707 | P120: 1456800 | Q120: 300000 | R120: =IFERROR(P120*(L120/100),"-") -> 1456800 | S120: =IFERROR(Q120*(L120/100),"-") -> 300000 | T120: =IFERROR((R120+S120)/(86*12),"-") -> 1702.3256 | U120: =O120-T120 -> 1370.8452 | V120: =U120/O120 -> 0.44606866 | W120: JD-TCI-BG4-BU4-ISG | X120: ISG | Y120: Rajesh Radhakrishnan Nair | Z120: Seshakishore Kumar Kollipara | AA120: Shailendra Gupta | AB120: Arun Kumar Mishra | AC120: BG4 | AD120: BG4-BU4 | AE120: 9 | AF120: INR
A121: 1008473 | B121: Jyoti Singh | C121: Resigned | D121: Permanent | E121: Sr. Test Engineer | F121: Rajesh Radhakrishnan Nair | G121: BG4 | H121: BG4-BU4 | I121: Testing | J121: Billable | K121: Billable | L121: 100 | M121: 1160 | N121: 0.012195122 | O121: =(L121/100)*M121*N121*(20*AE121) -> 2546.3415 | P121: 1503300 | Q121: 300000 | R121: =IFERROR(P121*(L121/100),"-") -> 1503300 | S121: =IFERROR(Q121*(L121/100),"-") -> 300000 | T121: =IFERROR((R121+S121)/(86*12),"-") -> 1747.3837 | U121: =O121-T121 -> 798.95774 | V121: =U121/O121 -> 0.31376693 | W121: JD-TCI-BG4-BU4-ISG | X121: ISG | Y121: Rajesh Radhakrishnan Nair | Z121: Seshakishore Kumar Kollipara | AA121: Shailendra Gupta | AB121: Arun Kumar Mishra | AC121: BG4 | AD121: BG4-BU4 | AE121: 9 | AF121: INR
A122: 1015059 | B122: Rishabh Singh Yadav | C122: Active | D122: Permanent | E122: Sr. Test Engineer | F122: Rajesh Radhakrishnan Nair | G122: BG4 | H122: BG4-BU4 | I122: Testing | J122: Billable | K122: Billable | L122: 100 | M122: 1400 | N122: 0.012195122 | O122: =(L122/100)*M122*N122*(20*AE122) -> 3073.1707 | P122: 1517508 | Q122: 300000 | R122: =IFERROR(P122*(L122/100),"-") -> 1517508 | S122: =IFERROR(Q122*(L122/100),"-") -> 300000 | T122: =IFERROR((R122+S122)/(86*12),"-") -> 1761.1512 | U122: =O122-T122 -> 1312.0196 | V122: =U122/O122 -> 0.426927 | W122: JD-TCI-BG4-BU4-ISG | X122: ISG | Y122: Rajesh Radhakrishnan Nair | Z122: Seshakishore Kumar Kollipara | AA122: Shailendra Gupta | AB122: Arun Kumar Mishra | AC122: BG4 | AD122: BG4-BU4 | AE122: 9 | AF122: INR
A123: 1017714 | B123: Shubham Jaiswal | C123: Active | D123: Permanent | E123: Sr. Software Engineer | F123: Rajesh Radhakrishnan Nair | G123: BG4 | H123: BG4-BU4 | I123: Java | J123: Billable | K123: Billable | L123: 100 | M123: 1300 | N123: 0.012195122 | O123: =(L123/100)*M123*N123*(20*AE123) -> 2853.6585 | P123: 1529100 | Q123: 300000 | R123: =IFERROR(P123*(L123/100),"-") -> 1529100 | S123: =IFERROR(Q123*(L123/100),"-") -> 300000 | T123: =IFERROR((R123+S123)/(86*12),"-") -> 1772.3837 | U123: =O123-T123 -> 1081.2748 | V123: =U123/O123 -> 0.37890827 | W123: JD-TCI-BG4-BU4-ISG | X123: ISG | Y123: Rajesh Radhakrishnan Nair | Z123: Seshakishore Kumar Kollipara | AA123: Shailendra Gupta | AB123: Arun Kumar Mishra | AC123: BG4 | AD123: BG4-BU4 | AE123: 9 | AF123: INR
A124: 1013222 | B124: Anoop Mehra | C124: Active | D124: Permanent | E124: Software Engineer | F124: Rajesh Radhakrishnan Nair | G124: BG4 | H124: BG4-BU4 | I124: Mobility | J124: Billable | K124: Billable | L124: 100 | M124: 1400 | N124: 0.012195122 | O124: =(L124/100)*M124*N124*(20*AE124) -> 3073.1707 | P124: 1550004 | Q124: 300000 | R124: =IFERROR(P124*(L124/100),"-") -> 1550004 | S124: =IFERROR(Q124*(L124/100),"-") -> 300000 | T124: =IFERROR((R124+S124)/(86*12),"-") -> 1792.6395 | U124: =O124-T124 -> 1280.5312 | V124: =U124/O124 -> 0.41668079 | W124: JD-TCI-BG4-BU4-ISG | X124: ISG | Y124: Rajesh Radhakrishnan Nair | Z124: Seshakishore Kumar Kollipara | AA124: Shailendra Gupta | AB124: Arun Kumar Mishra | AC124: BG4 | AD124: BG4-BU4 | AE124: 9 | AF124: INR
... A133: 1015978 | B133: Kanha Shivam Mishra | C133: Active | D133: Permanent | E133: Sr. Software Engineer | F133: Rajesh Radhakrishnan Nair | G133: BG4 | H133: BG4-BU4 | I133: Mainframe | J133: Billable | K133: Billable | L133: 100 | M133: 1400 | N133: 0.012195122 | O133: =(L133/100)*M133*N133*(20*AE133) -> 3073.1707 | P133: 1764204 | Q133: 300000 | R133: =IFERROR(P133*(L133/100),"-") -> 1764204 | S133: =IFERROR(Q133*(L133/100),"-") -> 300000 | T133: =IFERROR((R133+S133)/(86*12),"-") -> 2000.1977 | U133: =O133-T133 -> 1072.9731 | V133: =U133/O133 -> 0.34914203 | W133: JD-TCI-BG4-BU4-IT Finance | X133: IT Finance | Y133: Rajesh Radhakrishnan Nair | Z133: Seshakishore Kumar Kollipara | AA133: Shailendra Gupta | AB133: Arun Kumar Mishra | AC133: BG4 | AD133: BG4-BU4 | AE133: 9 | AF133: INR
A134: 1000111 | B134: Madhu Smitha | I134: SAP | V134: 0.42911905 | X134: IT Finance
A135: 1013812 | B135: Jeshwant Kolan | I135: SAP | V135: 0.43771429 | X135: IT Finance
A136: 1100051 | B136: Akash Bhutwani | I136: SAP | V136: 0.58811765 | X136: IT Finance
A137: 1014827 | B137: Shradha Agnibhoj | C137: Active | D137: Permanent | E137: Software Engineer | F137: Rajesh Radhakrishnan Nair | G137: BG4 | H137: BG4-BU4 | I137: AWS - App Dev | J137: Billable | K137: Billable | L137: 100 | M137: 1200 | N137: 0.012195122 | O137: =(L137/100)*M137*N137*(20*AE137) -> 2634.1463 | P137: 824208 | Q137: 300000 | R137: =IFERROR(P137*(L137/100),"-") -> 824208 | S137: =IFERROR(Q137*(L137/100),"-") -> 300000 | T137: =IFERROR((R137+S137)/(86*12),"-") -> 1089.3488 | U137: =O137-T137 -> 1544.7975 | V137: =U137/O137 -> 0.5864509 | W137: JD-TCI-BG4-BU4-JDF | X137: JDF | Y137: Rajesh Radhakrishnan Nair | Z137: Seshakishore Kumar Kollipara | AA137: Shailendra Gupta | AB137: Arun Kumar Mishra | AC137: BG4 | AD137: BG4-BU4 | AE137: 9 | AF137: INR
A138: 1016671 | B138: Shubham Sharadchand Patil | C138: Active | D138: Permanent | E138: Software Engineer | F138: Rajesh Radhakrishnan Nair | G138: BG4 | H138: BG4-BU4 | I138: Java | J138: Billable | K138: Billable | L138: 100 | M138: 1200 | N138: 0.012195122 | O138: =(L138/100)*M138*N138*(20*AE138) -> 2634.1463 | P138: 909504 | Q138: 300000 | R138: =IFERROR(P138*(L138/100),"-") -> 909504 | S138: =IFERROR(Q138*(L138/100),"-") -> 300000 | T138: =IFERROR((R138+S138)/(86*12),"-") -> 1172 | U138: =O138-T138 -> 1462.1463 | V138: =U138/O138 -> 0.55507407 | W138: JD-TCI-BG4-BU4-JDF | X138: JDF | Y138: Rajesh Radhakrishnan Nair | Z138: Seshakishore Kumar Kollipara | AA138: Shailendra Gupta | AB138: Arun Kumar Mishra | AC138: BG4 | AD138: BG4-BU4 | AE138: 9 | AF138: INR
A139: 1010368 | B139: Venkata Manikanta Attili | C139: Active | D139: Permanent | E139: Sr. Consultant | F139: Rajesh Radhakrishnan Nair | G139: BG4 | H139: BG4-BU2 | I139: Oracle | J139: Billable | K139: Billable | L139: 100 | M139: 1800 | N139: 0.012195122 | O139: =(L139/100)*M139*N139*(20*AE139) -> 3951.2195 | P139: 1732104 | Q139: 300000 | R139: =IFERROR(P139*(L139/100),"-") -> 1732104 | S139: =IFERROR(Q139*(L139/100),"-") -> 300000 | T139: =IFERROR((R139+S139)/(86*12),"-") -> 1969.093 | U139: =O139-T139 -> 1982.1265 | V139: =U139/O139 -> 0.5016493 | W139: JD-TCI-BG4-BU4-JDF | X139: JDF | Y139: Rajesh Radhakrishnan Nair | Z139: Seshakishore Kumar Kollipara | AA139: Shailendra Gupta | AB139: Arun Kumar Mishra | AC139: BG4 | AD139: BG4-BU4 | AE139: 9 | AF139: INR
A140: 1010804 | B140: Anas Fakir Mohammed Shaikh | C140: Active | D140: Permanent | E140: Sr. Software Engineer | F140: Rajesh Radhakrishnan Nair | G140: BG4 | H140: BG4-BU2 | I140: Oracle | J140: Billable | K140: Billable | L140: 100 | M140: 1800 | N140: 0.012195122 | O140: =(L140/100)*M140*N140*(20*AE140) -> 3951.2195 | P140: 1795500 | Q140: 300000 | R140: =IFERROR(P140*(L140/100),"-") -> 1795500 | S140: =IFERROR(Q140*(L140/100),"-") -> 300000 | T140: =IFERROR((R140+S140)/(86*12),"-") -> 2030.5233 | U140: =O140-T140 -> 1920.6963 | V140: =U140/O140 -> 0.48610214 | W140: JD-TCI-BG4-BU4-JDF | X140: JDF | Y140: Rajesh Radhakrishnan Nair | Z140: Seshakishore Kumar Kollipara | AA140: Shailendra Gupta | AB140: Arun Kumar Mishra | AC140: BG4 | AD140: BG4-BU4 | AE140: 9 | AF140: INR
A141: 1017706 | B141: Manoj Kumbhkar | C141: Active | D141: Permanent | E141: Sr. Software Engineer | F141: Rajesh Radhakrishnan Nair | G141: BG4 | H141: BG4-BU4 | I141: Java | J141: Billable | K141: Billable | L141: 100 | M141: 1700 | N141: 0.012195122 | O141: =(L141/100)*M141*N141*(20*AE141) -> 3731.7073 | P141: 1800000 | Q141: 300000 | R141: =IFERROR(P141*(L141/100),"-") -> 1800000 | S141: =IFERROR(Q141*(L141/100),"-") -> 300000 | T141: =IFERROR((R141+S141)/(86*12),"-") -> 2034.8837 | U141: =O141-T141 -> 1696.8236 | V141: =U141/O141 -> 0.45470436 | W141: JD-TCI-BG4-BU4-JDF | X141: JDF | Y141: Rajesh Radhakrishnan Nair | Z141: Seshakishore Kumar Kollipara | AA141: Shailendra Gupta | AB141: Arun Kumar Mishra | AC141: BG4 | AD141: BG4-BU4 | AE141: 9 | AF141: INR
A142: 1017512 | B142: Mayur Shivaji Sontale | C142: Active | D142: Permanent | E142: Module Lead | F142: Rajesh Radhakrishnan Nair | G142: BG4 | H142: BG4-BU4 | I142: Java | J142: Billable | K142: Billable | L142: 100 | M142: 1800 | N142: 0.012195122 | O142: =(L142/100)*M142*N142*(20*AE142) -> 3951.2195 | P142: 1899904 | Q142: 300000 | R142: =IFERROR(P142*(L142/100),"-") -> 1899904 | S142: =IFERROR(Q142*(L142/100),"-") -> 300000 | T142: =IFERROR((R142+S142)/(86*12),"-") -> 2131.6899 | U142: =O142-T142 -> 1819.5296 | V142: =U142/O142 -> 0.46049823 | W142: JD-TCI-BG4-BU4-JDF | X142: JDF | Y142: Rajesh Radhakrishnan Nair | Z142: Seshakishore Kumar Kollipara | AA142: Shailendra Gupta | AB142: Arun Kumar Mishra | AC142: BG4 | AD142: BG4-BU4 | AE142: 9 | AF142: INR
A143: 1013920 | B143: Abhishek Rai | C143: Active | D143: Permanent | E143: Module Lead | F143: Rajesh Radhakrishnan Nair | G143: BG4 | H143: BG4-BU4 | I143: Java | J143: Billable | K143: Billable | L143: 100 | M143: 2100 | N143: 0.012195122 | O143: =(L143/100)*M143*N143*(20*AE143) -> 4609.7561 | P143: 2110700 | Q143: 300000 | R143: =IFERROR(P143*(L143/100),"-") -> 2110700 | S143: =IFERROR(Q143*(L143/100),"-") -> 300000 | T143: =IFERROR((R143+S143)/(86*12),"-") -> 2335.9496 | U143: =O143-T143 -> 2273.8065 | V143: =U143/O143 -> 0.49325961 | W143: JD-TCI-BG4-BU4-JDF | X143: JDF | Y143: Rajesh Radhakrishnan Nair | Z143: Seshakishore Kumar Kollipara | AA143: Shailendra Gupta | AB143: Arun Kumar Mishra | AC143: BG4 | AD143: BG4-BU4 | AE143: 9 | AF143: INR
A144: 1010965 | B144: Titash Roy | C144: Active | D144: Permanent | E144: Tech Lead | F144: Rajesh Radhakrishnan Nair | G144: BG4 | H144: BG4-BU4 | I144: Java | J144: Billable | K144: Billable | L144: 100 | M144: 2100 | N144: 0.012195122 | O144: =(L144/100)*M144*N144*(20*AE144) -> 4609.7561 | P144: 2693900 | Q144: 300000 | R144: =IFERROR(P144*(L144/100),"-") -> 2693900 | S144: =IFERROR(Q144*(L144/100),"-") -> 300000 | T144: =IFERROR((R144+S144)/(86*12),"-") -> 2901.0659 | U144: =O144-T144 -> 1708.6902 | V144: =U144/O144 -> 0.37066825 | W144: JD-TCI-BG4-BU4-JDF | X144: JDF | Y144: Rajesh Radhakrishnan Nair | Z144: Seshakishore Kumar Kollipara | AA144: Shailendra Gupta | AB144: Arun Kumar Mishra | AC144: BG4 | AD144: BG4-BU4 | AE144: 9 | AF144: INR
A145: 1011045 | B145: Virendra . | C145: Active | D145: Permanent | E145: Tech Lead | F145: Rajesh Radhakrishnan Nair | G145: BG4 | H145: BG4-BU4 | I145: Java | J145: Billable | K145: Billable | L145: 100 | M145: 2100 | N145: 0.012195122 | O145: =(L145/100)*M145*N145*(20*AE145) -> 4609.7561 | P145: 2861008 | Q145: 300000 | R145: =IFERROR(P145*(L145/100),"-") -> 2861008 | S145: =IFERROR(Q145*(L145/100),"-") -> 300000 | T145: =IFERROR((R145+S145)/(86*12),"-") -> 3062.9922 | U145: =O145-T145 -> 1546.7638 | V145: =U145/O145 -> 0.33554136 | W145: JD-TCI-BG4-BU4-JDF | X145: JDF | Y145: Rajesh Radhakrishnan Nair | Z145: Seshakishore Kumar Kollipara | AA145: Shailendra Gupta | AB145: Arun Kumar Mishra | AC145: BG4 | AD145: BG4-BU4 | AE145: 9 | AF145: INR
A146: 1012234 | B146: Subhojeet Santra | I146: SAP | V146: 0.68608824 | X146: JDF
A147: 1101133 | B147: Shweta Dilip Dokhe | C147: Active | D147: Permanent | E147: Sr. Software Engineer | F147: Rajesh Radhakrishnan Nair | G147: BG4 | H147: BG4-BU4 | I147: Java | J147: Billable | K147: Billable | L147: 100 | M147: 1700 | N147: 0.012195122 | O147: =(L147/100)*M147*N147*(20*AE147) -> 3731.7073 | P147: 1200000 | Q147: 300000 | R147: =IFERROR(P147*(L147/100),"-") -> 1200000 | S147: =IFERROR(Q147*(L147/100),"-") -> 300000 | T147: =IFERROR((R147+S147)/(86*12),"-") -> 1453.4884 | U147: =O147-T147 -> 2278.2189 | V147: =U147/O147 -> 0.61050312 | W147: JD-TCI-BG4-BU4-MSP | X147: MSP | Y147: Rajesh Radhakrishnan Nair | Z147: Seshakishore Kumar Kollipara | AA147: Shailendra Gupta | AB147: Arun Kumar Mishra | AC147: BG4 | AD147: BG4-BU4 | AE147: 9 | AF147: INR
A148: 1015842 | B148: Ankita Rathi | C148: Active | D148: Permanent | E148: Sr. Software Engineer | F148: Rajesh Radhakrishnan Nair | G148: BG4 | H148: BG4-BU4 | I148: Java | J148: Billable | K148: Billable | L148: 100 | M148: 1400 | N148: 0.012195122 | O148: =(L148/100)*M148*N148*(20*AE148) -> 3073.1707 | P148: 1350108 | Q148: 300000 | R148: =IFERROR(P148*(L148/100),"-") -> 1350108 | S148: =IFERROR(Q148*(L148/100),"-") -> 300000 | T148: =IFERROR((R148+S148)/(86*12),"-") -> 1598.9419 | U148: =O148-T148 -> 1474.2289 | V148: =U148/O148 -> 0.47970939 | W148: JD-TCI-BG4-BU4-MSP | X148: MSP | Y148: Rajesh Radhakrishnan Nair | Z148: Seshakishore Kumar Kollipara | AA148: Shailendra Gupta | AB148: Arun Kumar Mishra | AC148: BG4 | AD148: BG4-BU4 | AE148: 9 | AF148: INR
A149: 1013003 | B149: Parikshit Abhimanyu Nemane | C149: Active | D149: Permanent | E149: UI Specialist | F149: Rajesh Radhakrishnan Nair | G149: BG5 | H149: BG5-BU1 | I149: User Interface (UI) | J149: Billable | K149: Billable | L149: 100 | M149: 1700 | N149: 0.012195122 | O149: =(L149/100)*M149*N149*(20*AE149) -> 3731.7073 | P149: 1500000 | Q149: 300000 | R149: =IFERROR(P149*(L149/100),"-") -> 1500000 | S149: =IFERROR(Q149*(L149/100),"-") -> 300000 | T149: =IFERROR((R149+S149)/(86*12),"-") -> 1744.186 | U149: =O149-T149 -> 1987.5213 | V149: =U149/O149 -> 0.53260374 | W149: JD-TCI-BG4-BU4-MSP | X149: MSP | Y149: Rajesh Radhakrishnan Nair | Z149: Seshakishore Kumar Kollipara | AA149: Shailendra Gupta | AB149: Arun Kumar Mishra | AC149: BG4 | AD149: BG4-BU4 | AE149: 9 | AF149: INR
A150: 1012589 | B150: Sowjanya Parthasarathi | I150: SAP | V150: 0.18699187 | X150: MSP
A151: 1012968 | B151: Narasimha Reddy Kanubuddi | I151: SAP | V151: 0.54552778 | X151: MSP
A152: 1601627 | B152: Sravani A | I152: SAP | V152: 0.3015873 | X152: MSP
A153: 1102132 | B153: Shivashankar Mallappa Nagur | I153: SAP | V153: 0.58928571 | X153: MSP
A154: 1014287 | B154: Shaily Rai | C154: Active | D154: Permanent | E154: Sr. Software Engineer | F154: Manish Gupta | G154: BG4 | H154: BG4-BU4 | I154: Java | J154: Billable | K154: Billable | L154: 100 | M154: 1700 | N154: 0.012195122 | O154: =(L154/100)*M154*N154*(20*AE154) -> 3731.7073 | P154: 1212600 | Q154: 300000 | R154: =IFERROR(P154*(L154/100),"-") -> 1212600 | S154: =IFERROR(Q154*(L154/100),"-") -> 300000 | T154: =IFERROR((R154+S154)/(86*12),"-") -> 1465.6977 | U154: =O154-T154 -> 2266.0096 | V154: =U154/O154 -> 0.60723134 | W154: JD-TCI-BG4-BU4-OM | X154: OM | Y154: Nilesh W Bansodkar | Z154: Seshakishore Kumar Kollipara | AA154: Shailendra Gupta | AB154: Arun Kumar Mishra | AC154: BG4 | AD154: BG4-BU4 | AE154: 9 | AF154: INR
A155: 1001573 | B155: Deepti Gupta | C155: Active | D155: Permanent | E155: Tech Lead | F155: Manish Gupta | G155: BG4 | H155: BG4-BU4 | I155: Java | J155: Billable | K155: Billable | L155: 100 | M155: 2300 | N155: 0.012195122 | O155: =(L155/100)*M155*N155*(20*AE155) -> 5048.7805 | P155: 1800204 | Q155: 300000 | R155: =IFERROR(P155*(L155/100),"-") -> 1800204 | S155: =IFERROR(Q155*(L155/100),"-") -> 300000 | T155: =IFERROR((R155+S155)/(86*12),"-") -> 2035.0814 | U155: =O155-T155 -> 3013.6991 | V155: =U155/O155 -> 0.59691625 | W155: JD-TCI-BG4-BU4-OM | X155: OM | Y155: Nilesh W Bansodkar | Z155: Seshakishore Kumar Kollipara | AA155: Shailendra Gupta | AB155: Arun Kumar Mishra | AC155: BG4 | AD155: BG4-BU4 | AE155: 9 | AF155: INR
A156: 1008483 | B156: Deependra Chaudhari | C156: Active | D156: Permanent | E156: Sr. Software Engineer | F156: Manish Gupta | G156: BG4 | H156: BG4-BU4 | I156: Java | J156: Billable | K156: Billable | L156: 100 | M156: 1800 | N156: 0.012195122 | O156: =(L156/100)*M156*N156*(20*AE156) -> 3951.2195 | P156: 1900008 | Q156: 300000 | R156: =IFERROR(P156*(L156/100),"-") -> 1900008 | S156: =IFERROR(Q156*(L156/100),"-") -> 300000 | T156: =IFERROR((R156+S156)/(86*12),"-") -> 2131.7907 | U156: =O156-T156 -> 1819.4288 | V156: =U156/O156 -> 0.46047272 | W156: JD-TCI-BG4-BU4-OM | X156: OM | Y156: Nilesh W Bansodkar | Z156: Seshakishore Kumar Kollipara | AA156: Shailendra Gupta | AB156: Arun Kumar Mishra | AC156: BG4 | AD156: BG4-BU4 | AE156: 9 | AF156: INR
A157: 1101180 | B157: Prem Gajanan Sharma | C157: Active | D157: Permanent | E157: Sr. Software Engineer | F157: Nilesh W Bansodkar | G157: BG4 | H157: BG4-BU4 | I157: Java | J157: Billable | K157: Billable | L157: 100 | M157: 1700 | N157: 0.012195122 | O157: =(L157/100)*M157*N157*(20*AE157) -> 3731.7073 | P157: 1000008 | Q157: 300000 | R157: =IFERROR(P157*(L157/100),"-") -> 1000008 | S157: =IFERROR(Q157*(L157/100),"-") -> 300000 | T157: =IFERROR((R157+S157)/(86*12),"-") -> 1259.6977 | U157: =O157-T157 -> 2472.0096 | V157: =U157/O157 -> 0.66243396 | W157: JD-TCI-BG4-BU4-PDC | X157: PDC | Y157: Nilesh W Bansodkar | Z157: Seshakishore Kumar Kollipara | AA157: Shailendra Gupta | AB157: Arun Kumar Mishra | AC157: BG4 | AD157: BG4-BU4 | AE157: 9 | AF157: INR
A158: 1010304 | B158: Uday Rajit Singh Panesar | C158: Active | D158: Permanent | E158: Sr. Software Engineer | F158: Nilesh W Bansodkar | G158: BG4 | H158: BG4-BU4 | I158: Microsoft | J158: Billable | K158: Billable | L158: 100 | M158: 1200 | N158: 0.012195122 | O158: =(L158/100)*M158*N158*(20*AE158) -> 2634.1463 | P158: 1197108 | Q158: 300000 | R158: =IFERROR(P158*(L158/100),"-") -> 1197108 | S158: =IFERROR(Q158*(L158/100),"-") -> 300000 | T158: =IFERROR((R158+S158)/(86*12),"-") -> 1450.686 | U158: =O158-T158 -> 1183.4603 | V158: =U158/O158 -> 0.44927659 | W158: JD-TCI-BG4-BU4-PDC | X158: PDC | Y158: Nilesh W Bansodkar | Z158: Seshakishore Kumar Kollipara | AA158: Shailendra Gupta | AB158: Arun Kumar Mishra | AC158: BG4 | AD158: BG4-BU4 | AE158: 9 | AF158: INR
A159: 1015715 | B159: Aniket Verma | C159: Active | D159: Permanent | E159: Sr. Software Engineer | F159: Nilesh W Bansodkar | G159: BG4 | H159: BG4-BU4 | I159: Mainframe | J159: Billable | K159: Billable | L159: 100 | M159: 1700 | N159: 0.012195122 | O159: =(L159/100)*M159*N159*(20*AE159) -> 3731.7073 | P159: 1253808 | Q159: 300000 | R159: =IFERROR(P159*(L159/100),"-") -> 1253808 | S159: =IFERROR(Q159*(L159/100),"-") -> 300000 | T159: =IFERROR((R159+S159)/(86*12),"-") -> 1505.6279 | U159: =O159-T159 -> 2226.0794 | V159: =U159/O159 -> 0.59653108 | W159: JD-TCI-BG4-BU4-PDC | X159: PDC | Y159: Nilesh W Bansodkar | Z159: Seshakishore Kumar Kollipara | AA159: Shailendra Gupta | AB159: Arun Kumar Mishra | AC159: BG4 | AD159: BG4-BU4 | AE159: 9 | AF159: INR
A160: 1017353 | B160: Ajfar Aziz | C160: Resigned | D160: Permanent | E160: Sr. Software Engineer | F160: Nilesh W Bansodkar | G160: BG4 | H160: BG4-BU4 | I160: Mainframe | J160: Billable | K160: Billable | L160: 100 | M160: 1700 | N160: 0.012195122 | O160: =(L160/100)*M160*N160*(20*AE160) -> 3731.7073 | P160: 1313208 | Q160: 300000 | R160: =IFERROR(P160*(L160/100),"-") -> 1313208 | S160: =IFERROR(Q160*(L160/100),"-") -> 300000 | T160: =IFERROR((R160+S160)/(86*12),"-") -> 1563.186 | U160: =O160-T160 -> 2168.5213 | V160: =U160/O160 -> 0.58110701 | W160: JD-TCI-BG4-BU4-PDC | X160: PDC | Y160: Nilesh W Bansodkar | Z160: Seshakishore Kumar Kollipara | AA160: Shailendra Gupta | AB160: Arun Kumar Mishra | AC160: BG4 | AD160: BG4-BU4 | AE160: 9 | AF160: INR
A161: 1017347 | B161: Doodala Sai Krishna | C161: Active | D161: Permanent | E161: Sr. Software Engineer | F161: Nilesh W Bansodkar | G161: BG4 | H161: BG4-BU4 | I161: Mainframe | J161: Billable | K161: Billable | L161: 100 | M161: 1700 | N161: 0.012195122 | O161: =(L161/100)*M161*N161*(20*AE161) -> 3731.7073 | P161: 1383708 | Q161: 300000 | R161: =IFERROR(P161*(L161/100),"-") -> 1383708 | S161: =IFERROR(Q161*(L161/100),"-") -> 300000 | T161: =IFERROR((R161+S161)/(86*12),"-") -> 1631.5 | U161: =O161-T161 -> 2100.2073 | V161: =U161/O161 -> 0.56280065 | W161: JD-TCI-BG4-BU4-PDC | X161: PDC | Y161: Nilesh W Bansodkar | Z161: Seshakishore Kumar Kollipara | AA161: Shailendra Gupta | AB161: Arun Kumar Mishra | AC161: BG4 | AD161: BG4-BU4 | AE161: 9 | AF161: INR
A162: 1014386 | B162: Ajit Raosaheb Bute | C162: Resigned | D162: Permanent | E162: Sr. Software Engineer | F162: Nilesh W Bansodkar | G162: BG4 | H162: BG4-BU4 | I162: Java | J162: Billable | K162: Billable | L162: 100 | M162: 1700 | N162: 0.012195122 | O162: =(L162/100)*M162*N162*(20*AE162) -> 3731.7073 | P162: 1436904 | Q162: 300000 | R162: =IFERROR(P162*(L162/100),"-") -> 1436904 | S162: =IFERROR(Q162*(L162/100),"-") -> 300000 | T162: =IFERROR((R162+S162)/(86*12),"-") -> 1683.0465 | U162: =O162-T162 -> 2048.6608 | V162: =U162/O162 -> 0.54898754 | W162: JD-TCI-BG4-BU4-PDC | X162: PDC | Y162: Nilesh W Bansodkar | Z162: Seshakishore Kumar Kollipara | AA162: Shailendra Gupta | AB162: Arun Kumar Mishra | AC162: BG4 | AD162: BG4-BU4 | AE162: 9 | AF162: INR
A163: 1016590 | B163: Tangella Yaswanth Sai Kalyan | C163: Active | D163: Permanent | E163: Sr. Software Engineer | F163: Nilesh W Bansodkar | G163: BG4 | H163: BG4-BU4 | I163: Mainframe | J163: Billable | K163: Billable | L163: 100 | M163: 1700 | N163: 0.012195122 | O163: =(L163/100)*M163*N163*(20*AE163) -> 3731.7073 | P163: 1510308 | Q163: 300000 | R163: =IFERROR(P163*(L163/100),"-") -> 1510308 | S163: =IFERROR(Q163*(L163/100),"-") -> 300000 | T163: =IFERROR((R163+S163)/(86*12),"-") -> 1754.1744 | U163: =O163-T163 -> 1977.5329 | V163: =U163/O163 -> 0.52992712 | W163: JD-TCI-BG4-BU4-PDC | X163: PDC | Y163: Nilesh W Bansodkar | Z163: Seshakishore Kumar Kollipara | AA163: Shailendra Gupta | AB163: Arun Kumar Mishra | AC163: BG4 | AD163: BG4-BU4 | AE163: 9 | AF163: INR
A164: 1101313 | B164: Ashwini Kishor Kasar | C164: Active | D164: Permanent | E164: Sr. Software Engineer | F164: Nilesh W Bansodkar | G164: BG4 | H164: BG4-BU4 | I164: Java | J164: Billable | K164: Billable | L164: 100 | M164: 1700 | N164: 0.012195122 | O164: =(L164/100)*M164*N164*(20*AE164) -> 3731.7073 | P164: 1550004 | Q164: 300000 | R164: =IFERROR(P164*(L164/100),"-") -> 1550004 | S164: =IFERROR(Q164*(L164/100),"-") -> 300000 | T164: =IFERROR((R164+S164)/(86*12),"-") -> 1792.6395 | U164: =O164-T164 -> 1939.0678 | V164: =U164/O164 -> 0.51961947 | W164: JD-TCI-BG4-BU4-PDC | X164: PDC | Y164: Nilesh W Bansodkar | Z164: Seshakishore Kumar Kollipara | AA164: Shailendra Gupta | AB164: Arun Kumar Mishra | AC164: BG4 | AD164: BG4-BU4 | AE164: 9 | AF164: INR
A165: 1010136 | B165: Veeraswamy Chitteti | C165: Active | D165: Permanent | E165: Module Lead | F165: Nilesh W Bansodkar | G165: BG4 | H165: BG4-BU4 | I165: Java | J165: Billable | K165: Billable | L165: 100 | M165: 1800 | N165: 0.012195122 | O165: =(L165/100)*M165*N165*(20*AE165) -> 3951.2195 | P165: 1724908 | Q165: 300000 | R165: =IFERROR(P165*(L165/100),"-") -> 1724908 | S165: =IFERROR(Q165*(L165/100),"-") -> 300000 | T165: =IFERROR((R165+S165)/(86*12),"-") -> 1962.1202 | U165: =O165-T165 -> 1989.0994 | V165: =U165/O165 -> 0.50341403 | W165: JD-TCI-BG4-BU4-PDC | X165: PDC | Y165: Nilesh W Bansodkar | Z165: Seshakishore Kumar Kollipara | AA165: Shailendra Gupta | AB165: Arun Kumar Mishra | AC165: BG4 | AD165: BG4-BU4 | AE165: 9 | AF165: INR
... A171: 1014547 | B171: Nirmal Kumar | C171: Active | D171: Permanent | E171: Module Lead | F171: Nilesh W Bansodkar | G171: BG4 | H171: BG4-BU4 | I171: Java | J171: Billable | K171: Billable | L171: 100 | M171: 2100 | N171: 0.012195122 | O171: =(L171/100)*M171*N171*(20*AE171) -> 4609.7561 | P171: 2468904 | Q171: 300000 | R171: =IFERROR(P171*(L171/100),"-") -> 2468904 | S171: =IFERROR(Q171*(L171/100),"-") -> 300000 | T171: =IFERROR((R171+S171)/(86*12),"-") -> 2683.0465 | U171: =O171-T171 -> 1926.7096 | V171: =U171/O171 -> 0.41796346 | W171: JD-TCI-BG4-BU4-PDC | X171: PDC | Y171: Nilesh W Bansodkar | Z171: Seshakishore Kumar Kollipara | AA171: Shailendra Gupta | AB171: Arun Kumar Mishra | AC171: BG4 | AD171: BG4-BU4 | AE171: 9 | AF171: INR
A172: 1601237 | B172: Akshay Upalekar | I172: SAP | V172: 0.33333333 | X172: PDC
A173: 1005949 | B173: B Sreedhar Reddy | I173: SAP | V173: 0.28 | X173: PDC
A174: 1012709 | B174: Kovvuru Chandra Reddy | I174: SAP | V174: 0.63885714 | X174: PDC
A175: 1014344 | B175: Sathi Manikanta Ramareddy | I175: SAP | V175: 0.72985294 | X175: PDC
A176: 1601466 | B176: Sreedevi Varahala | I176: SAP | V176: 0.43181818 | X176: PDC
A177: 1600057 | B177: Afsar Mohammad | I177: SAP | V177: 0.45508333 | X177: PDC
A178: 1601535 | B178: Yanamadala Sasidhar | I178: SAP | V178: 0.25531915 | X178: PDC
A179: 1601630 | B179: B Kiran Kumar | I179: SAP | V179: 0.25531915 | X179: PDC | AG179: 49
A180: 1601656 | B180: Nagam Rammohan | I180: SAP | V180: 0.22857143 | X180: PDC | AG180: 45
A181: 1601660 | B181: G Ravi Prasanna | I181: SAP | V181: 0.23529412 | X181: PDC
A182: 1014265 | B182: Bojja Prabhanjan | I182: SAP | V182: 0.73169444 | X182: PDC
A183: 1601741 | B183: Keerthana K | I183: SAP | V183: 0.33333333 | X183: PDC
A184: 1015679 | B184: Manisha Velivela | I184: SAP | V184: 0.63804167 | X184: PDC
A185: 1008331 | B185: Nischala Boppa | I185: SAP | V185: 0.44203571 | X185: PDC
A186: 1602021 | B186: Rajini Duggirala | I186: SAP | V186: 0.26785714 | X186: PDC
A187: 1602082 | B187: Nisha | I187: SAP | V187: 0.25 | X187: PDC
A188: 1602253 | B188: Tisha Haria | I188: SAP | V188: 0.31916667 | X188: PDC
A189: 1602284 | B189: Naga Jyothi Maddali | I189: SAP | V189: 0.29 | X189: PDC
A190: 1100837 | B190: Shubham Kishor Gajare | C190: Active | D190: Permanent | E190: Software Engineer | F190: Rajesh Radhakrishnan Nair | G190: BG4 | H190: BG4-BU4 | I190: Java | J190: Billable | K190: Billable | L190: 100 | M190: 1200 | N190: 0.012195122 | O190: =(L190/100)*M190*N190*(20*AE190) -> 2634.1463 | P190: 500004 | Q190: 300000 | R190: =IFERROR(P190*(L190/100),"-") -> 500004 | S190: =IFERROR(Q190*(L190/100),"-") -> 300000 | T190: =IFERROR((R190+S190)/(86*12),"-") -> 775.19767 | U190: =O190-T190 -> 1858.9487 | V190: =U190/O190 -> 0.70571199 | W190: JD-TCI-BG4-BU4-PDP | X190: PDP | Y190: Rajesh Radhakrishnan Nair | Z190: Seshakishore Kumar Kollipara | AA190: Shailendra Gupta | AB190: Arun Kumar Mishra | AC190: BG4 | AD190: BG4-BU4 | AE190: 9 | AF190: INR
A191: 1101033 | B191: Dipali Bhoyar | C191: Resigned | D191: Permanent | E191: Software Engineer | F191: Rajesh Radhakrishnan Nair | G191: BG4 | H191: BG4-BU4 | I191: Java | J191: Billable | K191: Billable | L191: 100 | M191: 900 | N191: 0.012195122 | O191: =(L191/100)*M191*N191*(20*AE191) -> 1975.6098 | P191: 650004 | Q191: 300000 | R191: =IFERROR(P191*(L191/100),"-") -> 650004 | S191: =IFERROR(Q191*(L191/100),"-") -> 300000 | T191: =IFERROR((R191+S191)/(86*12),"-") -> 920.54651 | U191: =O191-T191 -> 1055.0632 | V191: =U191/O191 -> 0.53404436 | W191: JD-TCI-BG4-BU4-PDP | X191: PDP | Y191: Rajesh Radhakrishnan Nair | Z191: Seshakishore Kumar Kollipara | AA191: Shailendra Gupta | AB191: Arun Kumar Mishra | AC191: BG4 | AD191: BG4-BU4 | AE191: 9 | AF191: INR
A192: 1101711 | B192: Anshul Harniya | C192: Active | D192: Permanent | E192: Software Engineer | F192: Rajesh Radhakrishnan Nair | G192: BG4 | H192: BG4-BU4 | I192: Java | J192: Billable | K192: Billable | L192: 100 | M192: 1200 | N192: 0.012195122 | O192: =(L192/100)*M192*N192*(20*AE192) -> 2634.1463 | P192: 650004 | Q192: 300000 | R192: =IFERROR(P192*(L192/100),"-") -> 650004 | S192: =IFERROR(Q192*(L192/100),"-") -> 300000 | T192: =IFERROR((R192+S192)/(86*12),"-") -> 920.54651 | U192: =O192-T192 -> 1713.5998 | V192: =U192/O192 -> 0.65053327 | W192: JD-TCI-BG4-BU4-PDP | X192: PDP | Y192: Rajesh Radhakrishnan Nair | Z192: Seshakishore Kumar Kollipara | AA192: Shailendra Gupta | AB192: Arun Kumar Mishra | AC192: BG4 | AD192: BG4-BU4 | AE192: 9 | AF192: INR
...

Sheet Sheet3
C2: Row Labels | D2: Sum of Profit%
C3: CAP | D3: 19.593167
C4: CPS | D4: 21.799754
C5: CPSS | D5: 0.44193842
C6: D&A | D6: 5.8414427
C7: Ecommerce | D7: 2.9420271
C8: ETEC | D8: 0.3893525
C9: Foundry | D9: 2.0557156
C10: HCM | D10: 1.3471667
C11: I&O | D11: 2.7041614
C12: ISG | D12: 5.1222139
C13: IT Finance | D13: 2.7251831
C14: JDF | D14: 4.9300365
... C20: Grand Total | D20: 99.349122
C25: CAP | D25: =4779%/100 -> 0.4779
C26: CPS | D26: =4954%/100 -> 0.4954
C27: CPSS | D27: =4419%/100 -> 0.4419
C28: D&A | D28: =5310%/100 -> 0.531
C29: eCommerce | D29: =4903%/100 -> 0.4903
C30: ETEC | D30: =3894%/100 -> 0.3894
C31: Foundry | D31: =5139%/100 -> 0.5139
C32: HCM | D32: =4491%/100 -> 0.4491
C33: I&O | D33: =4507%/100 -> 0.4507
C34: ISG | D34: =4269%/100 -> 0.4269
C35: IT Finance | D35: =4542%/100 -> 0.4542
C36: JDF | D36: =4930%/100 -> 0.493
C37: MSP | D37: =4637%/100 -> 0.4637
C38: OM | D38: =5549%/100 -> 0.5549
C39: PDC | D39: =4465%/100 -> 0.4465
C40: PDP | D40: =5220%/100 -> 0.522
C41: R1OF | D41: =4137%/100 -> 0.4137

Sheet Employee detail
A1: Sr no | B1: YASH Emp ID | C1: Name | D1: Contingent/Contractor | E1: Status | F1: Domain | G1: Group Name | H1: Skill | I1: Sub Skill | J1: Biling Rate in INR
A2: 1 | B2: 1000111 | C2: Madhu Smitha Kola | D2: Contractor | E2: Active | F2: IT Finance | G2: IT Finance | H2: SAP | I2: SAP FI | J2: 2100
A3: 2 | B3: 1004759 | C3: Anoop Halder | D3: Contingent | E3: Active | F3: PDP | G3: Product Design PV&V | H3: Testing | I3: QA | J3: 1400
A4: 3 | B4: 1005949 | C4: Sreedhar Reddy Bonala | D4: Contractor | E4: Active | F4: PDC | G4: Parts Mordenization | H4: SAP | I4: SAP CRM | J4: 1500
A5: 4 | B5: 1007148 | C5: Atul Laxmanrao Vairale | D5: Contingent | E5: Active | F5: CPS | G5: CPS- Resolution and Information | H5: Fullstack | I5: JAVA | J5: 1800
A6: 5 | B6: 1007362 | C6: Anwar Bashirahmad Kudle | D6: Contingent | E6: Active | F6: I&O | G6: Platform Services/Cloud | H6: Mainframe | I6: DBA | J6: 1700
A7: 6 | B7: 1006932 | C7: Vikram Karan Pingale | D7: Contingent | E7: Active | F7: ISG | G7: ISG - Digital, Shared Services | H7: Testing | I7: QA | J7: 2000
A8: 7 | B8: 1008048 | C8: Mahesh Anil Thokala | D8: Contingent | E8: Active | F8: CPS | G8: CPS - Proactive Services | H8: Testing | I8: QA | J8: 1400
A9: 8 | B9: 1008172 | C9: Shailendrakumar Amarsing Vasave | D9: Contingent | E9: Active | F9: PDP | G9: Product Design PV&V | H9: SQL Server DBA | I9: .NET | J9: 1700
A10: 9 | B10: 1008473 | C10: Jyoti Singh | D10: Contingent | E10: Inactive | F10: ISG | G10: ISG - Digital, Reprogramming and Activation | H10: Testing | I10: QA | J10: 1160
A11: 10 | B11: 1008531 | C11: Prachi Sanmesh Kale | D11: Contingent | E11: Active | F11: I&O | G11: Platform Services/Cloud | H11: Fullstack | I11: JAVA Cloud | J11: 1800
A12: 11 | B12: 1009357 | C12: Harshal Ketan Patil | D12: Contingent | E12: Active | F12: Foundry | G12: Quality & Reliability | H12: Fullstack | I12: JAVA | J12: 1800
A13: 12 | B13: 1009451 | C13: Vrushabh Abhaykumar Wakhariya | D13: Contingent | E13: Active | F13: Ecommerce | G13: Channel Systems & Services | H13: Fullstack | I13: JAVA | J13: 1700
... A75: 74 | B75: 1016619 | C75: Pratik Venkatesh Kurbet | D75: Contingent | E75: Active | F75: CPS | G75: CPS- Resolution and Information | H75: Fullstack | I75: JAVA | J75: 1700
A76: 75 | B76: 1011907 | C76: Nayan Pimpare | D76: Project | E76: Active | F76: MSP | G76: Manufacturing Engineering | H76: UI/UX | I76: UI | J76: Fixed Bid
A77: 76 | B77: 1600057 | C77: Shaaleen Mohammad Afsar Syed Hussain | D77: Contractor | E77: Active | F77: PDC | G77: Parts Order management | H77: SAP | I77: SAP BODS | J77: 1800
A78: 77 | B78: 1017372 | C78: Aadesh Mishra | D78: Contingent | E78: Active | F78: PDP | G78: Product Data Management | H78: Fullstack | I78: Fullstack | J78: 1700
A79: 78 | B79: 1017347 | C79: Sai Krishna Doodla | D79: Contingent | E79: Active | F79: PDC | G79: Parts Warehousing, Planning | H79: Mainframe | I79: Mainframe | J79: 1700
A80: 79 | B80: 1017397 | C80: Akash Jadhav | D80: Contingent | E80: Active | F80: CPS | G80: CPS- Resolution and Information | H80: DATA | I80: Python | J80: 1800
A81: 80 | B81: 1601535 | C81: Yanamadala Sasidhar | D81: Contingent | E81: Active | F81: PDC | G81: Parts Mordenization | H81: SAP | I81: SAP CRM | J81: 2350
A82: 81 | B82: 1017492 | C82: Vatsal Shah Dharmendra | D82: Contingent | E82: Active | F82: CPS | G82: CPS - Proactive Services | H82: Fullstack | I82: Embedded C++ | J82: 1800
A83: 82 | B83: 1016969 | C83: Venkataraman J | D83: Contingent | E83: Active | F83: PDP | G83: Product Data management | H83: SAP | I83: SAP | J83: 1800
A84: 83 | B84: 1015753 | C84: Sushant Temkar | D84: Project | E84: Active | F84: MSP | G84: Manufacturing Engineering | H84: Fullstack | I84: Fullstack | J84: Fixed Bid
A85: 84 | B85: 1016893 | C85: Mahima Shrivastav | D85: Contingent | E85: Active | F85: CPS | G85: CPS- Resolution and Information | H85: Fullstack | I85: Core Java | J85: 1200
A86: 85 | B86: 1016671 | C86: Shubham Patil | D86: Contingent | E86: Active | F86: JDF | G86: DevOps Operations | H86: Fullstack | I86: Java | J86: 1200
A87: 86 | B87: 1017512 | C87: Mayur Sontale | D87: Contingent | E87: Active | F87: JDF | G87: JDF - Platform Services | H87: Fullstack | I87: Java Aws | J87: 1800
A88: 87 | B88: 1004516 | C88: Bhaskar Yellamanchili | D88: Contractor | E88: Active | F88: HCM | G88: HR and Corporate Functions | H88: SAP | I88: SAP HR | J88: 1800
A89: 88 | B89: 1015066 | C89: Aman Kumar 1 | D89: Contingent | E89: Active | F89: CPS | G89: CPS - Proactive Services | H89: Fullstack | I89: JAVA+React | J89: 1200
A90: 89 | B90: 1013812 | C90: Jeshwant Kumar Kolan | D90: Contingent | E90: Active | F90: IT Finance | G90: IT Finance | H90: SAP | I90: SAP ABAP | J90: 1400
A91: 90 | B91: 1014208 | C91: Priyanshi Zamindar | D91: Contingent | E91: Active | F91: ETEC | G91: ETEC | H91: Fullstack | I91: JAVA+React | J91: 1700
A92: 91 | B92: 1015478 | C92: Ramdas Buttanwad | D92: Contingent | E92: Active | F92: ISG | G92: ISG - Digital | H92: Fullstack | I92: Java Script | J92: 1300
A93: 92 | B93: 1016683 | C93: Shubhangi Kamble | D93: Project | E93: Active | F93: MSP | G93: Manufacturing Engineering | H93: Fullstack | I93: Fullstack | J93: Fixed Bid
A94: 93 | B94: 1100011 | C94: Manish Madhukar Yadav | D94: Contingent | E94: Active | F94: Ecommerce | G94: Ecommerce | H94: DATA | I94: Data Engenniering | J94: 1700
A95: 94 | B95: 1601630 | C95: Balineni Kiran Kumar Reddy | D95: Contingent | E95: Active | F95: PDC | G95: Parts Warehousing, Planning | H95: SAP | I95: SAP CRM | J95: 2350
A96: 95 | B96: 1017777 | C96: Swati Patil | D96: Contingent | E96: Active | F96: CPS | G96: CPS- Resolution and Information | H96: SAP | I96: SAP ABAP | J96: 2100
A97: 96 | B97: 1601627 | C97: Sravani Ananthapalli | D97: Project | E97: Active | F97: MSP | G97: Manufacturing Engineering | H97: SAP | I97: SAP ABAP | J97: Fixed Bid
A98: 97 | B98: 1012589 | C98: Sowjanya Parthasarathi | D98: Project | E98: Active | F98: MSP | G98: Manufacturing Engineering | H98: SAP | I98: SAP PI/PO | J98: Fixed Bid
A99: 98 | B99: 1100076 | C99: Rahul Mhakave | D99: Contingent | E99: Active | F99: D&A | G99: Data Products | H99: DATA | I99: Data engineering | J99: 2100
A100: 99 | B100: 1100051 | C100: Akash Bhutwani | D100: Contingent | E100: Active | F100: IT Finance | G100: IT Finance | H100: SAP | I100: SAP | J100: 1700
A101: 100 | B101: 1006133 | C101: Vishal Sarathe | D101: Contingent | E101: Active | F101: ISG | G101: ISG - Digital | H101: Testing | I101: Testing | J101: 1800
A102: 101 | B102: 1601656 | C102: Nagam Rammohan Rao | D102: Contractor | E102: Active | F102: PDC | G102: Parts Warehousing, Planning | H102: SAP | I102: SAP CRM | J102: 2100
A103: 102 | B103: 1601660 | C103: Ravi Kumar | D103: Contractor | E103: Inactive | F103: PDC | G103: Parts Warehousing, Planning | H103: SAP | I103: SAP CRM | J103: 1700
A104: 103 | B104: 1100163 | C104: Akash Sahebrao Kadhane | D104: Contingent | E104: Active | F104: D&A | G104: Data Products | H104: DATA | I104: Data engineering | J104: 2100
A105: 104 | B105: 1100125 | C105: Vikram Vinayak Kurade | D105: Contingent | E105: Active | F105: Ecommerce | G105: Ecommerce | H105: DATA | I105: Data Engenniering | J105: 1800
A106: 105 | B106: 1100167 | C106: Bhavika Patil | D106: Contingent | E106: Active | F106: CPS | G106: CPS- Resolution and Information | H106: DATA | I106: Python | J106: 1400
A107: 106 | B107: 1013003 | C107: Parikshit Abhimanyu Nemane | D107: Contingent | E107: Active | F107: MSP | G107: Manufacturing Engineering | H107: UI/UX | I107: UI/UX | J107: 1700
A108: 107 | B108: 1017706 | C108: Manoj Kumbhkar | D108: Contingent | E108: Active | F108: JDF | G108: JDF-Dealer | H108: Fullstack | I108: Fullstack | J108: 1700
A109: 108 | B109: 1017714 | C109: Shubham Jaiswal | D109: Contingent | E109: Active | F109: ISG | G109: ISG - Digital, Reprogramming and Activation | H109: Fullstack | I109: Fullstack | J109: 1300
A110: 109 | B110: 1100284 | C110: Omkar Vaibhav Shinde | D110: Contingent | E110: Active | F110: ISG | G110: ISG - Digital, Reprogramming and Activation | H110: Mobility | I110: Android | J110: 1400
... A123: 122 | B123: 1009263 | C123: Monika Patil | D123: Contingent | E123: Active | F123: CPS | G123: CPS- Resolution and Information | H123: DevOps | I123: DevOps | J123: 1700
A124: 123 | B124: 1007109 | C124: Ruchi Sarawagi | D124: Project | E124: Active | F124: MSP | G124: Manufacturing Engineering | H124: Fullstack | I124: Fullstack | J124: Fixed Bid
A125: 124 | B125: 1100515 | C125: Shubham Giri | D125: Contingent | E125: Active | F125: CAP | G125: Marketing and Sales | H125: DATA | I125: Data Engenering | J125: 1400
A126: 125 | B126: 1100583 | C126: Kaushiki Tapadiya | D126: Contingent | E126: Active | F126: CAP | G126: Marketing and Sales | H126: Fullstack | I126: Fullstack | J126: 1400
A127: 126 | B127: 1100625 | C127: Praveen Bhende | D127: Contingent | E127: Active | F127: PDP | G127: Product Data management | H127: DevOps | I127: DevOps | J127: 1700
A128: 127 | B128: 1012437 | C128: Gaurav Patil | D128: Contingent | E128: Active | F128: CAP | G128: Marketing and Sales | H128: Altova | I128: Java + Altova | J128: 1200
A129: 128 | B129: 1015842 | C129: Ankita Rathi | D129: Contingent | E129: Active | F129: MSP | G129: Manufacturing Engineering | H129: Fullstack | I129: Fullstack | J129: 1400
A130: 129 | B130: 1100468 | C130: Pooja Ambawle | D130: Contingent | E130: Active | F130: D&A | G130: Data Products | H130: Mainframe | I130: Mainframe | J130: 1800
A131: 130 | B131: 1100729 | C131: Shefali Goyal | D131: Contingent | E131: Active | F131: CPS | G131: CPS- Resolution and Information | H131: Fullstack | I131: Fullstack | J131: 1700
A132: 131 | B132: 1016717 | C132: Arun Kumar | D132: Contingent | E132: Active | F132: CAP | G132: Marketing and Sales | H132: Altova | I132: Altova | J132: 1400
A133: 132 | B133: 1100752 | C133: Priti Naik | D133: Contingent | E133: Active | F133: I&O | G133: Platform Services/Cloud | H133: Service Now | I133: Service Now | J133: 1800
A134: 133 | B134: 1015679 | C134: Manisha Velivela | D134: Contingent | E134: Active | F134: PDC | G134: Parts Warehousing, Planning | H134: SAP | I134: SAP BODS | J134: 1200
A135: 134 | B135: 1100745 | C135: Pushpak Bhambar | D135: Contingent | E135: Active | F135: CAP | G135: Marketing and Sales | H135: Fullstack | I135: Fullstack | J135: 1200
A136: 135 | B136: 1100770 | C136: Yatish K | D136: Contingent | E136: Active | F136: CAP | G136: Dealer Business Systems - Customer and Channel IT | H136: MS Dynamics | I136: Microsoft Dynamics | J136: 1400
... A143: 142 | B143: 1101133 | C143: Shweta Dilip Dokhe | D143: Contingent | E143: Active | F143: MSP | G143: Manufacturing Engineering | H143: Fullstack | I143: Fullstack | J143: 1700
A144: 143 | B144: 1015939 | C144: Pradeep Kale | D144: Project | E144: Active | F144: CAP | G144: Marketing and Sales | H144: Mobility | I144: Android | J144: Fixed Bid
A145: 144 | B145: 1013786 | C145: Krishna Yadav | D145: Project | E145: Active | F145: CAP | G145: Marketing and Sales | H145: Mobility | I145: Android | J145: Fixed Bid
A146: 145 | B146: 1015431 | C146: Amir Sohel | D146: Project | E146: Active | F146: CAP | G146: Marketing and Sales | H146: Mobility | I146: Android | J146: Fixed Bid
A147: 146 | B147: 1011367 | C147: Avinash Singh | D147: Contingent | E147: Active | F147: CAP | G147: Dealer Business Systems - Customer and Channel IT | H147: MS Dynamics | I147: Microsoft Dynamics | J147: 1400
A148: 147 | B148: 1015712 | C148: Ajeet Gupta | D148: Contingent | E148: Active | F148: CAP | G148: Markting and Sales | H148: Fullstack | I148: Fullstack | J148: 2100
A149: 148 | B149: 1101262 | C149: Prashant Dubey | D149: Contingent | E149: Active | F149: CPS | G149: CPS - Proactive Services | H149: Fullstack | I149: Fullstack | J149: 1700
A150: 149 | B150: 1009270 | C150: Anuja Ajab | D150: Contingent | E150: Active | F150: Foundry | G150: Quality Operation | H150: Power Apps | I150: Power Apps | J150: 1800
A151: 150 | B151: 1013437 | C151: Kalpana Jadhav | D151: Contingent | E151: Active | F151: Foundry | G151: Quality Operation | H151: Power Apps | I151: Power Apps | J151: 1800
A152: 151 | B152: 1101276 | C152: Harshal Patil | D152: Contingent | E152: Active | F152: CAP | G152: Dealer Business Systems - Customer and Channel IT | H152: DATA | I152: Infomatica | J152: 2100
A153: 152 | B153: 1101306 | C153: Edde Rajasekhar Reddy | D153: Contingent | E153: Active | F153: CAP | G153: Dealer Business Systems - Customer and Channel IT | H153: MS Dynamics | I153: Microsoft Dynamics | J153: 1700
A154: 153 | B154: 1101300 | C154: Aman Mishra | D154: Contingent | E154: Active | F154: CPS | G154: CPS- Resolution and Information | H154: Fullstack | I154: React | J154: 1700
A155: 154 | B155: 1101374 | C155: Kshitiz Kothari | D155: Contingent | E155: Active | F155: CPS | G155: CPS- Resolution and Information | H155: DATA | I155: Python and DataBricks | J155: 1800
A156: 155 | B156: 1602021 | C156: Rajini Duggirala | D156: Contractor | E156: Active | F156: PDC | G156: Parts Warehousing, Planning | H156: SAP | I156: SAP | J156: 2800
A157: 156 | B157: 1101014 | C157: Nishant Kamble | D157: Contingent | E157: Active | F157: PDC | G157: Parts Warehousing, Planning | H157: Fullstack | I157: JAVA | J157: 2100
A158: 157 | B158: 1101314 | C158: Himanshu Chowhan | D158: Contingent | E158: Active | F158: Ecommerce | G158: Ecommerce | H158: Testing | I158: Testing | J158: 1400
A159: 158 | B159: 1101517 | C159: Nikhil Agrawal | D159: Contingent | E159: Active | F159: CPS | G159: CPS- Resolution and Information | H159: DATA | J159: 1700
A160: 159 | B160: 1101327 | C160: Akshay Ramteke | D160: Contingent | E160: Active | F160: ISG | G160: ISG - Digital,Ops CTR.Mobile | H160: UI/UX | J160: 1800
A161: 160 | B161: 1101033 | C161: Dipali Bhoyar | D161: Contingent | E161: Active | F161: PDP | G161: Product Data management | H161: Fullstack | I161: Java +React | J161: 900
A162: 161 | B162: 1016906 | C162: Durga Prasad J | D162: Contingent | E162: Active | F162: D&A | G162: Data Products | H162: Mainframe | J162: 1500
A163: 162 | B163: 1602082 | C163: Nisha S | D163: Contractor | E163: Active | F163: PDC | G163: Parts Warehousing, Planning | H163: SAP | I163: SAP | J163: 2400
A164: 163 | B164: 1101521 | C164: Mullamuri Bhargavi | D164: Contingent | E164: Active | F164: CAP | G164: Dealer Business Systems - Customer and Channel IT | H164: MS Dynamics | I164: Microsoft Dynamics | J164: 1400
A165: 164 | B165: 1000110 | C165: Jai Kumar Gadoeya | D165: Contractor | E165: Active | F165: D&A | G165: Data Products | H165: DATA | J165: 2100
A166: 165 | B166: 1001573 | C166: Deepti Gupta | D166: Contingent | E166: Active | F166: OM | G166: JDPS Marketing | H166: Fullstack | J166: 2300
A167: 166 | B167: 1008483 | C167: Deependra Choudhary | D167: Contingent | E167: Active | F167: OM | G167: JDPS Marketing | H167: Fullstack | J167: 1800
A168: 167 | B168: 1101599 | C168: Pranesh Subhash Nanoskar | D168: Contingent | E168: Active | F168: CPS | G168: CPS- Resolution and Information | H168: Fullstack | I168: react/node js + Java. | J168: 1700
A169: 168 | B169: 1101611 | C169: Prabin Kumar Baitharu | D169: Contingent | E169: Active | F169: I&O | G169: Platform Services/Cloud | H169: Service Now | I169: Service Now | J169: 2100
A170: 169 | B170: 1101556 | C170: Amanaganti Vamshi Reddy | D170: Contingent | E170: Active | F170: CAP | G170: Dealer Business Systems - Customer and Channel IT | H170: MS Dynamics | I170: Microsoft Dynamics | J170: 1400
A171: 170 | B171: 1007687 | C171: Sarika Kate | D171: Contingent | E171: Active | F171: ISG | G171: ISG - Digital, Shared Services | H171: Mobility | I171: Mobility | J171: 1700
A172: 171 | B172: 1101180 | C172: Prem Sharma | D172: Contingent | E172: Active | F172: PDC | G172: Parts Warehousing, Planning | H172: Fullstack | I172: Java +React | J172: 1700
A173: 172 | B173: 1101621 | C173: Upasna C | D173: Contingent | E173: Active | F173: CPS | G173: CPS- Resolution and Information | H173: Fullstack | I173: Java + React+AWS | J173: 1700
A174: 173 | B174: 1101688 | C174: Shantanu Mithilesh Moraskar | D174: Contingent | E174: Active | F174: D&A | G174: Data Products | H174: Fullstack | I174: Java +React | J174: 1700
A175: 174 | B175: 1101270 | C175: Kalyani Shiromani Meshram | D175: Contingent | E175: Active | F175: IT Finance | G175: IT Finance | H175: Mainframe | J175: 1400
A176: 175 | B176: 1101719 | C176: Akshay Mahadev Ovhal | D176: Contingent | E176: Active | F176: CAP | G176: Dealer Business Systems - Customer and Channel IT | H176: DATA | I176: informatica | J176: 1700
A177: 176 | B177: 1101722 | C177: Snehal Bhimrao Tapare | D177: Contingent | E177: Active | F177: CAP | G177: Dealer Business Systems - Customer and Channel IT | H177: MS Dynamics | I177: Microsoft Dynamics | J177: 2100
A178: 177 | B178: 1101795 | C178: Anvitha Maindan | D178: Contingent | E178: Active | F178: R1OF | H178: RPA | J178: 1550
A179: 178 | B179: 1017742 | C179: Govind Kurmi | D179: Contingent | E179: Active | F179: Ecommerce | G179: Marketing and Sales | H179: Fullstack | I179: Java Spring Boot | J179: 1700
...
